Workbook

Sheet final_phase2_full_costs
A1: House_ID | B1: Market | C1: Phase | D1: Tier | E1: Buy_Month | F1: Sell_Month | G1: Holding_Period | H1: Buy_Price | I1: Rehab_Cost | J1: Appreciation_Gain | K1: Uplift_Gain | L1: Sell_Price | M1: Insurance_Cost | N1: Property_Tax_Cost | O1: Maintenance_Cost | P1: HOA_Cost | Q1: Total_Holding_Cost | R1: Buy_Txn_Cost | S1: Sell_Txn_Cost | T1: Service_Fee_Buy | U1: Service_Fee_Sell | V1: Profit
A2: 1 | B2: Dallas | C2: 2 | D2: Tier 1 | E2: 13 | F2: 17 | G2: 4 | H2: 338000 | I2: 27642.992 | J2: 4447.8785 | K2: 27642.992 | L2: 397733.86 | M2: 450.66667 | N2: 2028 | O2: 240 | P2: 200 | Q2: 2918.6667 | R2: 3380 | S2: 4772.8063 | T2: 10140 | U2: 11932.016 | V2: =L2-H2 -> 59733.862
A3: 2 | B3: Dallas | C3: 2 | D3: Tier 1 | E3: 13 | F3: 17 | G3: 4 | H3: 338000 | I3: 27642.992 | J3: 4447.8785 | K3: 27642.992 | L3: 397733.86 | M3: 450.66667 | N3: 2028 | O3: 240 | P3: 200 | Q3: 2918.6667 | R3: 3380 | S3: 4772.8063 | T3: 10140 | U3: 11932.016 | V3: =L3-H3 -> 59733.862
V4: =SUM(V2:V3) -> 119467.72
A5: 3 | B5: Dallas | C5: 2 | D5: Tier 2 | E5: 13 | F5: 18 | G5: 5 | H5: 443000 | I5: 27172.734 | J5: 8199.7468 | K5: 27172.734 | L5: 505545.21 | M5: 738.33333 | N5: 3322.5 | O5: 300 | P5: 250 | Q5: 4610.8333 | R5: 4430 | S5: 6066.5426 | T5: 13290 | U5: 15166.356 | V5: =L5-H5 -> 62545.215
A6: 4 | B6: Dallas | C6: 2 | D6: Tier 2 | E6: 13 | F6: 18 | G6: 5 | H6: 443000 | I6: 27172.734 | J6: 8199.7468 | K6: 27172.734 | L6: 505545.21 | M6: 738.33333 | N6: 3322.5 | O6: 300 | P6: 250 | Q6: 4610.8333 | R6: 4430 | S6: 6066.5426 | T6: 13290 | U6: 15166.356 | V6: =L6-H6 -> 62545.215
A7: 5 | B7: Dallas | C7: 2 | D7: Tier 2 | E7: 13 | F7: 18 | G7: 5 | H7: 443000 | I7: 27172.734 | J7: 8199.7468 | K7: 27172.734 | L7: 505545.21 | M7: 738.33333 | N7: 3322.5 | O7: 300 | P7: 250 | Q7: 4610.8333 | R7: 4430 | S7: 6066.5426 | T7: 13290 | U7: 15166.356 | V7: =L7-H7 -> 62545.215
A8: 8 | B8: Dallas | C8: 2 | D8: Tier 1 | E8: 14 | F8: 18 | G8: 4 | H8: 338000 | I8: 27642.992 | J8: 4447.8785 | K8: 27642.992 | L8: 397733.86 | M8: 450.66667 | N8: 2028 | O8: 240 | P8: 200 | Q8: 2918.6667 | R8: 3380 | S8: 4772.8063 | T8: 10140 | U8: 11932.016 | V8: =L8-H8 -> 59733.862
A9: 9 | B9: Dallas | C9: 2 | D9: Tier 1 | E9: 14 | F9: 18 | G9: 4 | H9: 338000 | I9: 27642.992 | J9: 4447.8785 | K9: 27642.992 | L9: 397733.86 | M9: 450.66667 | N9: 2028 | O9: 240 | P9: 200 | Q9: 2918.6667 | R9: 3380 | S9: 4772.8063 | T9: 10140 | U9: 11932.016 | V9: =L9-H9 -> 59733.862
A10: 11 | B10: Dallas | C10: 2 | D10: Tier 1 | E10: 14 | F10: 18 | G10: 4 | H10: 338000 | I10: 27642.992 | J10: 4447.8785 | K10: 27642.992 | L10: 397733.86 | M10: 450.66667 | N10: 2028 | O10: 240 | P10: 200 | Q10: 2918.6667 | R10: 3380 | S10: 4772.8063 | T10: 10140 | U10: 11932.016 | V10: =L10-H10 -> 59733.862
A11: 22 | B11: Dallas | C11: 2 | D11: Tier 1 | E11: 15 | F11: 18 | G11: 3 | H11: 338000 | I11: 27642.992 | J11: 3330.4514 | K11: 27642.992 | L11: 396616.44 | M11: 338 | N11: 1521 | O11: 180 | P11: 150 | Q11: 2189 | R11: 3380 | S11: 4759.3972 | T11: 10140 | U11: 11898.493 | V11: =L11-H11 -> 58616.435
V12: =SUM(V5:V11) -> 425453.67
A13: 6 | B13: Dallas | C13: 2 | D13: Tier 2 | E13: 13 | F13: 19 | G13: 6 | H13: 443000 | I13: 27172.734 | J13: 9857.8199 | K13: 27172.734 | L13: 507203.29 | M13: 886 | N13: 3987 | O13: 360 | P13: 300 | Q13: 5533 | R13: 4430 | S13: 6086.4395 | T13: 13290 | U13: 15216.099 | V13: =L13-H13 -> 64203.288
A14: 7 | B14: Dallas | C14: 2 | D14: Tier 3 | E14: 13 | F14: 19 | G14: 6 | H14: 676000 | I14: 34553.74 | J14: 16693.872 | K14: 34553.74 | L14: 761801.35 | M14: 1352 | N14: 6084 | O14: 360 | P14: 300 | Q14: 8096 | R14: 6760 | S14: 9141.6162 | T14: 20280 | U14: 22854.041 | V14: =L14-H14 -> 85801.352
A15: 10 | B15: Dallas | C15: 2 | D15: Tier 1 | E15: 14 | F15: 19 | G15: 5 | H15: 338000 | I15: 27642.992 | J15: 5568.9637 | K15: 27642.992 | L15: 398854.95 | M15: 563.33333 | N15: 2535 | O15: 300 | P15: 250 | Q15: 3648.3333 | R15: 3380 | S15: 4786.2594 | T15: 10140 | U15: 11965.648 | V15: =L15-H15 -> 60854.948
A16: 14 | B16: Dallas | C16: 2 | D16: Tier 2 | E16: 14 | F16: 19 | G16: 5 | H16: 443000 | I16: 27172.734 | J16: 8199.7468 | K16: 27172.734 | L16: 505545.21 | M16: 738.33333 | N16: 3322.5 | O16: 300 | P16: 250 | Q16: 4610.8333 | R16: 4430 | S16: 6066.5426 | T16: 13290 | U16: 15166.356 | V16: =L16-H16 -> 62545.215
A17: 16 | B17: Dallas | C17: 2 | D17: Tier 2 | E17: 14 | F17: 19 | G17: 5 | H17: 443000 | I17: 27172.734 | J17: 8199.7468 | K17: 27172.734 | L17: 505545.21 | M17: 738.33333 | N17: 3322.5 | O17: 300 | P17: 250 | Q17: 4610.8333 | R17: 4430 | S17: 6066.5426 | T17: 13290 | U17: 15166.356 | V17: =L17-H17 -> 62545.215
A18: 21 | B18: Dallas | C18: 2 | D18: Tier 1 | E18: 15 | F18: 19 | G18: 4 | H18: 338000 | I18: 27642.992 | J18: 4447.8785 | K18: 27642.992 | L18: 397733.86 | M18: 450.66667 | N18: 2028 | O18: 240 | P18: 200 | Q18: 2918.6667 | R18: 3380 | S18: 4772.8063 | T18: 10140 | U18: 11932.016 | V18: =L18-H18 -> 59733.862
A19: 25 | B19: Dallas | C19: 2 | D19: Tier 2 | E19: 15 | F19: 19 | G19: 4 | H19: 443000 | I19: 27172.734 | J19: 6547.7445 | K19: 27172.734 | L19: 503893.21 | M19: 590.66667 | N19: 2658 | O19: 240 | P19: 200 | Q19: 3688.6667 | R19: 4430 | S19: 6046.7186 | T19: 13290 | U19: 15116.796 | V19: =L19-H19 -> 60893.213
A20: 26 | B20: Dallas | C20: 2 | D20: Tier 2 | E20: 15 | F20: 19 | G20: 4 | H20: 443000 | I20: 27172.734 | J20: 6547.7445 | K20: 27172.734 | L20: 503893.21 | M20: 590.66667 | N20: 2658 | O20: 240 | P20: 200 | Q20: 3688.6667 | R20: 4430 | S20: 6046.7186 | T20: 13290 | U20: 15116.796 | V20: =L20-H20 -> 60893.213
A21: 28 | B21: Dallas | C21: 2 | D21: Tier 2 | E21: 15 | F21: 19 | G21: 4 | H21: 443000 | I21: 27172.734 | J21: 6547.7445 | K21: 27172.734 | L21: 503893.21 | M21: 590.66667 | N21: 2658 | O21: 240 | P21: 200 | Q21: 3688.6667 | R21: 4430 | S21: 6046.7186 | T21: 13290 | U21: 15116.796 | V21: =L21-H21 -> 60893.213
A22: 31 | B22: Dallas | C22: 2 | D22: Tier 1 | E22: 16 | F22: 19 | G22: 3 | H22: 338000 | I22: 27642.992 | J22: 3330.4514 | K22: 27642.992 | L22: 396616.44 | M22: 338 | N22: 1521 | O22: 180 | P22: 150 | Q22: 2189 | R22: 3380 | S22: 4759.3972 | T22: 10140 | U22: 11898.493 | V22: =L22-H22 -> 58616.435
A23: 33 | B23: Dallas | C23: 2 | D23: Tier 1 | E23: 16 | F23: 19 | G23: 3 | H23: 338000 | I23: 27642.992 | J23: 3330.4514 | K23: 27642.992 | L23: 396616.44 | M23: 338 | N23: 1521 | O23: 180 | P23: 150 | Q23: 2189 | R23: 3380 | S23: 4759.3972 | T23: 10140 | U23: 11898.493 | V23: =L23-H23 -> 58616.435
A24: 34 | B24: Dallas | C24: 2 | D24: Tier 1 | E24: 16 | F24: 19 | G24: 3 | H24: 338000 | I24: 27642.992 | J24: 3330.4514 | K24: 27642.992 | L24: 396616.44 | M24: 338 | N24: 1521 | O24: 180 | P24: 150 | Q24: 2189 | R24: 3380 | S24: 4759.3972 | T24: 10140 | U24: 11898.493 | V24: =L24-H24 -> 58616.435
V25: =SUM(V13:V24) -> 754212.82
A26: 12 | B26: Dallas | C26: 2 | D26: Tier 2 | E26: 14 | F26: 20 | G26: 6 | H26: 443000 | I26: 27172.734 | J26: 9857.8199 | K26: 27172.734 | L26: 507203.29 | M26: 886 | N26: 3987 | O26: 360 | P26: 300 | Q26: 5533 | R26: 4430 | S26: 6086.4395 | T26: 13290 | U26: 15216.099 | V26: =L26-H26 -> 64203.288
A27: 13 | B27: Dallas | C27: 2 | D27: Tier 2 | E27: 14 | F27: 20 | G27: 6 | H27: 443000 | I27: 27172.734 | J27: 9857.8199 | K27: 27172.734 | L27: 507203.29 | M27: 886 | N27: 3987 | O27: 360 | P27: 300 | Q27: 5533 | R27: 4430 | S27: 6086.4395 | T27: 13290 | U27: 15216.099 | V27: =L27-H27 -> 64203.288
A28: 15 | B28: Dallas | C28: 2 | D28: Tier 2 | E28: 14 | F28: 20 | G28: 6 | H28: 443000 | I28: 27172.734 | J28: 9857.8199 | K28: 27172.734 | L28: 507203.29 | M28: 886 | N28: 3987 | O28: 360 | P28: 300 | Q28: 5533 | R28: 4430 | S28: 6086.4395 | T28: 13290 | U28: 15216.099 | V28: =L28-H28 -> 64203.288
A29: 17 | B29: Dallas | C29: 2 | D29: Tier 3 | E29: 14 | F29: 20 | G29: 6 | H29: 676000 | I29: 34553.74 | J29: 16693.872 | K29: 34553.74 | L29: 761801.35 | M29: 1352 | N29: 6084 | O29: 360 | P29: 300 | Q29: 8096 | R29: 6760 | S29: 9141.6162 | T29: 20280 | U29: 22854.041 | V29: =L29-H29 -> 85801.352
A30: 18 | B30: Dallas | C30: 2 | D30: Tier 1 | E30: 15 | F30: 20 | G30: 5 | H30: 338000 | I30: 27642.992 | J30: 5568.9637 | K30: 27642.992 | L30: 398854.95 | M30: 563.33333 | N30: 2535 | O30: 300 | P30: 250 | Q30: 3648.3333 | R30: 3380 | S30: 4786.2594 | T30: 10140 | U30: 11965.648 | V30: =L30-H30 -> 60854.948
A31: 19 | B31: Dallas | C31: 2 | D31: Tier 1 | E31: 15 | F31: 20 | G31: 5 | H31: 338000 | I31: 27642.992 | J31: 5568.9637 | K31: 27642.992 | L31: 398854.95 | M31: 563.33333 | N31: 2535 | O31: 300 | P31: 250 | Q31: 3648.3333 | R31: 3380 | S31: 4786.2594 | T31: 10140 | U31: 11965.648 | V31: =L31-H31 -> 60854.948
A32: 20 | B32: Dallas | C32: 2 | D32: Tier 1 | E32: 15 | F32: 20 | G32: 5 | H32: 338000 | I32: 27642.992 | J32: 5568.9637 | K32: 27642.992 | L32: 398854.95 | M32: 563.33333 | N32: 2535 | O32: 300 | P32: 250 | Q32: 3648.3333 | R32: 3380 | S32: 4786.2594 | T32: 10140 | U32: 11965.648 | V32: =L32-H32 -> 60854.948
A33: 30 | B33: Dallas | C33: 2 | D33: Tier 3 | E33: 15 | F33: 20 | G33: 5 | H33: 676000 | I33: 34553.74 | J33: 13883.202 | K33: 34553.74 | L33: 758990.68 | M33: 1126.6667 | N33: 5070 | O33: 300 | P33: 250 | Q33: 6746.6667 | R33: 6760 | S33: 9107.8882 | T33: 20280 | U33: 22769.72 | V33: =L33-H33 -> 82990.682
A34: 38 | B34: Dallas | C34: 2 | D34: Tier 2 | E34: 16 | F34: 20 | G34: 4 | H34: 443000 | I34: 27172.734 | J34: 6547.7445 | K34: 27172.734 | L34: 503893.21 | M34: 590.66667 | N34: 2658 | O34: 240 | P34: 200 | Q34: 3688.6667 | R34: 4430 | S34: 6046.7186 | T34: 13290 | U34: 15116.796 | V34: =L34-H34 -> 60893.213
A35: 42 | B35: Dallas | C35: 2 | D35: Tier 2 | E35: 16 | F35: 20 | G35: 4 | H35: 443000 | I35: 27172.734 | J35: 6547.7445 | K35: 27172.734 | L35: 503893.21 | M35: 590.66667 | N35: 2658 | O35: 240 | P35: 200 | Q35: 3688.6667 | R35: 4430 | S35: 6046.7186 | T35: 13290 | U35: 15116.796 | V35: =L35-H35 -> 60893.213
V36: =SUM(V26:V35) -> 665753.17
A37: 23 | B37: Dallas | C37: 2 | D37: Tier 2 | E37: 15 | F37: 21 | G37: 6 | H37: 443000 | I37: 27172.734 | J37: 9857.8199 | K37: 27172.734 | L37: 507203.29 | M37: 886 | N37: 3987 | O37: 360 | P37: 300 | Q37: 5533 | R37: 4430 | S37: 6086.4395 | T37: 13290 | U37: 15216.099 | V37: =L37-H37 -> 64203.288
A38: 24 | B38: Dallas | C38: 2 | D38: Tier 2 | E38: 15 | F38: 21 | G38: 6 | H38: 443000 | I38: 27172.734 | J38: 9857.8199 | K38: 27172.734 | L38: 507203.29 | M38: 886 | N38: 3987 | O38: 360 | P38: 300 | Q38: 5533 | R38: 4430 | S38: 6086.4395 | T38: 13290 | U38: 15216.099 | V38: =L38-H38 -> 64203.288
A39: 27 | B39: Dallas | C39: 2 | D39: Tier 2 | E39: 15 | F39: 21 | G39: 6 | H39: 443000 | I39: 27172.734 | J39: 9857.8199 | K39: 27172.734 | L39: 507203.29 | M39: 886 | N39: 3987 | O39: 360 | P39: 300 | Q39: 5533 | R39: 4430 | S39: 6086.4395 | T39: 13290 | U39: 15216.099 | V39: =L39-H39 -> 64203.288
A40: 32 | B40: Dallas | C40: 2 | D40: Tier 1 | E40: 16 | F40: 21 | G40: 5 | H40: 338000 | I40: 27642.992 | J40: 5568.9637 | K40: 27642.992 | L40: 398854.95 | M40: 563.33333 | N40: 2535 | O40: 300 | P40: 250 | Q40: 3648.3333 | R40: 3380 | S40: 4786.2594 | T40: 10140 | U40: 11965.648 | V40: =L40-H40 -> 60854.948
A41: 35 | B41: Dallas | C41: 2 | D41: Tier 1 | E41: 16 | F41: 21 | G41: 5 | H41: 338000 | I41: 27642.992 | J41: 5568.9637 | K41: 27642.992 | L41: 398854.95 | M41: 563.33333 | N41: 2535 | O41: 300 | P41: 250 | Q41: 3648.3333 | R41: 3380 | S41: 4786.2594 | T41: 10140 | U41: 11965.648 | V41: =L41-H41 -> 60854.948
A42: 36 | B42: Dallas | C42: 2 | D42: Tier 1 | E42: 16 | F42: 21 | G42: 5 | H42: 338000 | I42: 27642.992 | J42: 5568.9637 | K42: 27642.992 | L42: 398854.95 | M42: 563.33333 | N42: 2535 | O42: 300 | P42: 250 | Q42: 3648.3333 | R42: 3380 | S42: 4786.2594 | T42: 10140 | U42: 11965.648 | V42: =L42-H42 -> 60854.948
A43: 40 | B43: Dallas | C43: 2 | D43: Tier 2 | E43: 16 | F43: 21 | G43: 5 | H43: 443000 | I43: 27172.734 | J43: 8199.7468 | K43: 27172.734 | L43: 505545.21 | M43: 738.33333 | N43: 3322.5 | O43: 300 | P43: 250 | Q43: 4610.8333 | R43: 4430 | S43: 6066.5426 | T43: 13290 | U43: 15166.356 | V43: =L43-H43 -> 62545.215
A44: 44 | B44: Dallas | C44: 2 | D44: Tier 2 | E44: 16 | F44: 21 | G44: 5 | H44: 443000 | I44: 27172.734 | J44: 8199.7468 | K44: 27172.734 | L44: 505545.21 | M44: 738.33333 | N44: 3322.5 | O44: 300 | P44: 250 | Q44: 4610.8333 | R44: 4430 | S44: 6066.5426 | T44: 13290 | U44: 15166.356 | V44: =L44-H44 -> 62545.215
A45: 47 | B45: Dallas | C45: 2 | D45: Tier 3 | E45: 16 | F45: 21 | G45: 5 | H45: 676000 | I45: 34553.74 | J45: 13883.202 | K45: 34553.74 | L45: 758990.68 | M45: 1126.6667 | N45: 5070 | O45: 300 | P45: 250 | Q45: 6746.6667 | R45: 6760 | S45: 9107.8882 | T45: 20280 | U45: 22769.72 | V45: =L45-H45 -> 82990.682
A46: 48 | B46: Dallas | C46: 2 | D46: Tier 1 | E46: 17 | F46: 21 | G46: 4 | H46: 338000 | I46: 27642.992 | J46: 4447.8785 | K46: 27642.992 | L46: 397733.86 | M46: 450.66667 | N46: 2028 | O46: 240 | P46: 200 | Q46: 2918.6667 | R46: 3380 | S46: 4772.8063 | T46: 10140 | U46: 11932.016 | V46: =L46-H46 -> 59733.862
A47: 49 | B47: Dallas | C47: 2 | D47: Tier 1 | E47: 17 | F47: 21 | G47: 4 | H47: 338000 | I47: 27642.992 | J47: 4447.8785 | K47: 27642.992 | L47: 397733.86 | M47: 450.66667 | N47: 2028 | O47: 240 | P47: 200 | Q47: 2918.6667 | R47: 3380 | S47: 4772.8063 | T47: 10140 | U47: 11932.016 | V47: =L47-H47 -> 59733.862
A48: 51 | B48: Dallas | C48: 2 | D48: Tier 1 | E48: 17 | F48: 21 | G48: 4 | H48: 338000 | I48: 27642.992 | J48: 4447.8785 | K48: 27642.992 | L48: 397733.86 | M48: 450.66667 | N48: 2028 | O48: 240 | P48: 200 | Q48: 2918.6667 | R48: 3380 | S48: 4772.8063 | T48: 10140 | U48: 11932.016 | V48: =L48-H48 -> 59733.862
... A61: 17 | B61: Atlanta | C61: 2 | D61: Tier 1 | E61: 17 | F61: 21 | G61: 4 | H61: 305000 | I61: 30500 | J61: 3019.9984 | K61: 27450 | L61: 365970 | M61: 508.33333 | N61: 1118.3333 | O61: 200 | P61: 160 | Q61: 1986.6667 | R61: 3050 | S61: 3659.7 | T61: 9150 | U61: 10979.1 | V61: =L61-H61 -> 60969.998
V62: =SUM(V37:V61) -> 1557559.5
A63: 29 | B63: Dallas | C63: 2 | D63: Tier 3 | E63: 15 | F63: 22 | G63: 7 | H63: 676000 | I63: 34553.74 | J63: 19515.992 | K63: 34553.74 | L63: 764623.47 | M63: 1577.3333 | N63: 7098 | O63: 420 | P63: 350 | Q63: 9445.3333 | R63: 6760 | S63: 9175.4817 | T63: 20280 | U63: 22938.704 | V63: =L63-H63 -> 88623.472
A64: 37 | B64: Dallas | C64: 2 | D64: Tier 2 | E64: 16 | F64: 22 | G64: 6 | H64: 443000 | I64: 27172.734 | J64: 9857.8199 | K64: 27172.734 | L64: 507203.29 | M64: 886 | N64: 3987 | O64: 360 | P64: 300 | Q64: 5533 | R64: 4430 | S64: 6086.4395 | T64: 13290 | U64: 15216.099 | V64: =L64-H64 -> 64203.288
A65: 39 | B65: Dallas | C65: 2 | D65: Tier 2 | E65: 16 | F65: 22 | G65: 6 | H65: 443000 | I65: 27172.734 | J65: 9857.8199 | K65: 27172.734 | L65: 507203.29 | M65: 886 | N65: 3987 | O65: 360 | P65: 300 | Q65: 5533 | R65: 4430 | S65: 6086.4395 | T65: 13290 | U65: 15216.099 | V65: =L65-H65 -> 64203.288
A66: 41 | B66: Dallas | C66: 2 | D66: Tier 2 | E66: 16 | F66: 22 | G66: 6 | H66: 443000 | I66: 27172.734 | J66: 9857.8199 | K66: 27172.734 | L66: 507203.29 | M66: 886 | N66: 3987 | O66: 360 | P66: 300 | Q66: 5533 | R66: 4430 | S66: 6086.4395 | T66: 13290 | U66: 15216.099 | V66: =L66-H66 -> 64203.288
A67: 43 | B67: Dallas | C67: 2 | D67: Tier 2 | E67: 16 | F67: 22 | G67: 6 | H67: 443000 | I67: 27172.734 | J67: 9857.8199 | K67: 27172.734 | L67: 507203.29 | M67: 886 | N67: 3987 | O67: 360 | P67: 300 | Q67: 5533 | R67: 4430 | S67: 6086.4395 | T67: 13290 | U67: 15216.099 | V67: =L67-H67 -> 64203.288
A68: 45 | B68: Dallas | C68: 2 | D68: Tier 3 | E68: 16 | F68: 22 | G68: 6 | H68: 676000 | I68: 34553.74 | J68: 16693.872 | K68: 34553.74 | L68: 761801.35 | M68: 1352 | N68: 6084 | O68: 360 | P68: 300 | Q68: 8096 | R68: 6760 | S68: 9141.6162 | T68: 20280 | U68: 22854.041 | V68: =L68-H68 -> 85801.352
A69: 46 | B69: Dallas | C69: 2 | D69: Tier 3 | E69: 16 | F69: 22 | G69: 6 | H69: 676000 | I69: 34553.74 | J69: 16693.872 | K69: 34553.74 | L69: 761801.35 | M69: 1352 | N69: 6084 | O69: 360 | P69: 300 | Q69: 8096 | R69: 6760 | S69: 9141.6162 | T69: 20280 | U69: 22854.041 | V69: =L69-H69 -> 85801.352
A70: 50 | B70: Dallas | C70: 2 | D70: Tier 1 | E70: 17 | F70: 22 | G70: 5 | H70: 338000 | I70: 27642.992 | J70: 5568.9637 | K70: 27642.992 | L70: 398854.95 | M70: 563.33333 | N70: 2535 | O70: 300 | P70: 250 | Q70: 3648.3333 | R70: 3380 | S70: 4786.2594 | T70: 10140 | U70: 11965.648 | V70: =L70-H70 -> 60854.948
A71: 53 | B71: Dallas | C71: 2 | D71: Tier 1 | E71: 17 | F71: 22 | G71: 5 | H71: 338000 | I71: 27642.992 | J71: 5568.9637 | K71: 27642.992 | L71: 398854.95 | M71: 563.33333 | N71: 2535 | O71: 300 | P71: 250 | Q71: 3648.3333 | R71: 3380 | S71: 4786.2594 | T71: 10140 | U71: 11965.648 | V71: =L71-H71 -> 60854.948
A72: 54 | B72: Dallas | C72: 2 | D72: Tier 1 | E72: 17 | F72: 22 | G72: 5 | H72: 338000 | I72: 27642.992 | J72: 5568.9637 | K72: 27642.992 | L72: 398854.95 | M72: 563.33333 | N72: 2535 | O72: 300 | P72: 250 | Q72: 3648.3333 | R72: 3380 | S72: 4786.2594 | T72: 10140 | U72: 11965.648 | V72: =L72-H72 -> 60854.948
A73: 55 | B73: Dallas | C73: 2 | D73: Tier 1 | E73: 17 | F73: 22 | G73: 5 | H73: 338000 | I73: 27642.992 | J73: 5568.9637 | K73: 27642.992 | L73: 398854.95 | M73: 563.33333 | N73: 2535 | O73: 300 | P73: 250 | Q73: 3648.3333 | R73: 3380 | S73: 4786.2594 | T73: 10140 | U73: 11965.648 | V73: =L73-H73 -> 60854.948
A74: 58 | B74: Dallas | C74: 2 | D74: Tier 2 | E74: 17 | F74: 22 | G74: 5 | H74: 443000 | I74: 27172.734 | J74: 8199.7468 | K74: 27172.734 | L74: 505545.21 | M74: 738.33333 | N74: 3322.5 | O74: 300 | P74: 250 | Q74: 4610.8333 | R74: 4430 | S74: 6066.5426 | T74: 13290 | U74: 15166.356 | V74: =L74-H74 -> 62545.215
... A95: 32 | B95: Atlanta | C95: 2 | D95: Tier 1 | E95: 18 | F95: 22 | G95: 4 | H95: 305000 | I95: 30500 | J95: 3019.9984 | K95: 27450 | L95: 365970 | M95: 508.33333 | N95: 1118.3333 | O95: 200 | P95: 160 | Q95: 1986.6667 | R95: 3050 | S95: 3659.7 | T95: 9150 | U95: 10979.1 | V95: =L95-H95 -> 60969.998
V96: =SUM(V63:V95) -> 2162024.5
A97: 56 | B97: Dallas | C97: 2 | D97: Tier 2 | E97: 17 | F97: 23 | G97: 6 | H97: 443000 | I97: 27172.734 | J97: 9857.8199 | K97: 27172.734 | L97: 507203.29 | M97: 886 | N97: 3987 | O97: 360 | P97: 300 | Q97: 5533 | R97: 4430 | S97: 6086.4395 | T97: 13290 | U97: 15216.099 | V97: =L97-H97 -> 64203.288
A98: 59 | B98: Dallas | C98: 2 | D98: Tier 2 | E98: 17 | F98: 23 | G98: 6 | H98: 443000 | I98: 27172.734 | J98: 9857.8199 | K98: 27172.734 | L98: 507203.29 | M98: 886 | N98: 3987 | O98: 360 | P98: 300 | Q98: 5533 | R98: 4430 | S98: 6086.4395 | T98: 13290 | U98: 15216.099 | V98: =L98-H98 -> 64203.288
A99: 60 | B99: Dallas | C99: 2 | D99: Tier 2 | E99: 17 | F99: 23 | G99: 6 | H99: 443000 | I99: 27172.734 | J99: 9857.8199 | K99: 27172.734 | L99: 507203.29 | M99: 886 | N99: 3987 | O99: 360 | P99: 300 | Q99: 5533 | R99: 4430 | S99: 6086.4395 | T99: 13290 | U99: 15216.099 | V99: =L99-H99 -> 64203.288
A100: 61 | B100: Dallas | C100: 2 | D100: Tier 2 | E100: 17 | F100: 23 | G100: 6 | H100: 443000 | I100: 27172.734 | J100: 9857.8199 | K100: 27172.734 | L100: 507203.29 | M100: 886 | N100: 3987 | O100: 360 | P100: 300 | Q100: 5533 | R100: 4430 | S100: 6086.4395 | T100: 13290 | U100: 15216.099 | V100: =L100-H100 -> 64203.288
A101: 65 | B101: Dallas | C101: 2 | D101: Tier 2 | E101: 17 | F101: 23 | G101: 6 | H101: 443000 | I101: 27172.734 | J101: 9857.8199 | K101: 27172.734 | L101: 507203.29 | M101: 886 | N101: 3987 | O101: 360 | P101: 300 | Q101: 5533 | R101: 4430 | S101: 6086.4395 | T101: 13290 | U101: 15216.099 | V101: =L101-H101 -> 64203.288
A102: 67 | B102: Dallas | C102: 2 | D102: Tier 2 | E102: 17 | F102: 23 | G102: 6 | H102: 443000 | I102: 27172.734 | J102: 9857.8199 | K102: 27172.734 | L102: 507203.29 | M102: 886 | N102: 3987 | O102: 360 | P102: 300 | Q102: 5533 | R102: 4430 | S102: 6086.4395 | T102: 13290 | U102: 15216.099 | V102: =L102-H102 -> 64203.288
A103: 71 | B103: Dallas | C103: 2 | D103: Tier 1 | E103: 18 | F103: 23 | G103: 5 | H103: 338000 | I103: 27642.992 | J103: 5568.9637 | K103: 27642.992 | L103: 398854.95 | M103: 563.33333 | N103: 2535 | O103: 300 | P103: 250 | Q103: 3648.3333 | R103: 3380 | S103: 4786.2594 | T103: 10140 | U103: 11965.648 | V103: =L103-H103 -> 60854.948
A104: 72 | B104: Dallas | C104: 2 | D104: Tier 1 | E104: 18 | F104: 23 | G104: 5 | H104: 338000 | I104: 27642.992 | J104: 5568.9637 | K104: 27642.992 | L104: 398854.95 | M104: 563.33333 | N104: 2535 | O104: 300 | P104: 250 | Q104: 3648.3333 | R104: 3380 | S104: 4786.2594 | T104: 10140 | U104: 11965.648 | V104: =L104-H104 -> 60854.948
A105: 73 | B105: Dallas | C105: 2 | D105: Tier 1 | E105: 18 | F105: 23 | G105: 5 | H105: 338000 | I105: 27642.992 | J105: 5568.9637 | K105: 27642.992 | L105: 398854.95 | M105: 563.33333 | N105: 2535 | O105: 300 | P105: 250 | Q105: 3648.3333 | R105: 3380 | S105: 4786.2594 | T105: 10140 | U105: 11965.648 | V105: =L105-H105 -> 60854.948
A106: 75 | B106: Dallas | C106: 2 | D106: Tier 1 | E106: 18 | F106: 23 | G106: 5 | H106: 338000 | I106: 27642.992 | J106: 5568.9637 | K106: 27642.992 | L106: 398854.95 | M106: 563.33333 | N106: 2535 | O106: 300 | P106: 250 | Q106: 3648.3333 | R106: 3380 | S106: 4786.2594 | T106: 10140 | U106: 11965.648 | V106: =L106-H106 -> 60854.948
A107: 77 | B107: Dallas | C107: 2 | D107: Tier 1 | E107: 18 | F107: 23 | G107: 5 | H107: 338000 | I107: 27642.992 | J107: 5568.9637 | K107: 27642.992 | L107: 398854.95 | M107: 563.33333 | N107: 2535 | O107: 300 | P107: 250 | Q107: 3648.3333 | R107: 3380 | S107: 4786.2594 | T107: 10140 | U107: 11965.648 | V107: =L107-H107 -> 60854.948
A108: 78 | B108: Dallas | C108: 2 | D108: Tier 1 | E108: 18 | F108: 23 | G108: 5 | H108: 338000 | I108: 27642.992 | J108: 5568.9637 | K108: 27642.992 | L108: 398854.95 | M108: 563.33333 | N108: 2535 | O108: 300 | P108: 250 | Q108: 3648.3333 | R108: 3380 | S108: 4786.2594 | T108: 10140 | U108: 11965.648 | V108: =L108-H108 -> 60854.948
... A153: 57 | B153: Atlanta | C153: 2 | D153: Tier 1 | E153: 19 | F153: 23 | G153: 4 | H153: 305000 | I153: 30500 | J153: 3019.9984 | K153: 27450 | L153: 365970 | M153: 508.33333 | N153: 1118.3333 | O153: 200 | P153: 160 | Q153: 1986.6667 | R153: 3050 | S153: 3659.7 | T153: 9150 | U153: 10979.1 | V153: =L153-H153 -> 60969.998
V154: =SUM(V97:V153) -> 3679469.2
A155: 69 | B155: Dallas | C155: 2 | D155: Tier 3 | E155: 17 | F155: 24 | G155: 7 | H155: 676000 | I155: 34553.74 | J155: 19515.992 | K155: 34553.74 | L155: 764623.47 | M155: 1577.3333 | N155: 7098 | O155: 420 | P155: 350 | Q155: 9445.3333 | R155: 6760 | S155: 9175.4817 | T155: 20280 | U155: 22938.704 | V155: =L155-H155 -> 88623.472
A156: 81 | B156: Dallas | C156: 2 | D156: Tier 2 | E156: 18 | F156: 24 | G156: 6 | H156: 443000 | I156: 27172.734 | J156: 9857.8199 | K156: 27172.734 | L156: 507203.29 | M156: 886 | N156: 3987 | O156: 360 | P156: 300 | Q156: 5533 | R156: 4430 | S156: 6086.4395 | T156: 13290 | U156: 15216.099 | V156: =L156-H156 -> 64203.288
A157: 83 | B157: Dallas | C157: 2 | D157: Tier 2 | E157: 18 | F157: 24 | G157: 6 | H157: 443000 | I157: 27172.734 | J157: 9857.8199 | K157: 27172.734 | L157: 507203.29 | M157: 886 | N157: 3987 | O157: 360 | P157: 300 | Q157: 5533 | R157: 4430 | S157: 6086.4395 | T157: 13290 | U157: 15216.099 | V157: =L157-H157 -> 64203.288
A158: 84 | B158: Dallas | C158: 2 | D158: Tier 2 | E158: 18 | F158: 24 | G158: 6 | H158: 443000 | I158: 27172.734 | J158: 9857.8199 | K158: 27172.734 | L158: 507203.29 | M158: 886 | N158: 3987 | O158: 360 | P158: 300 | Q158: 5533 | R158: 4430 | S158: 6086.4395 | T158: 13290 | U158: 15216.099 | V158: =L158-H158 -> 64203.288
A159: 86 | B159: Dallas | C159: 2 | D159: Tier 2 | E159: 18 | F159: 24 | G159: 6 | H159: 443000 | I159: 27172.734 | J159: 9857.8199 | K159: 27172.734 | L159: 507203.29 | M159: 886 | N159: 3987 | O159: 360 | P159: 300 | Q159: 5533 | R159: 4430 | S159: 6086.4395 | T159: 13290 | U159: 15216.099 | V159: =L159-H159 -> 64203.288
A160: 87 | B160: Dallas | C160: 2 | D160: Tier 2 | E160: 18 | F160: 24 | G160: 6 | H160: 443000 | I160: 27172.734 | J160: 9857.8199 | K160: 27172.734 | L160: 507203.29 | M160: 886 | N160: 3987 | O160: 360 | P160: 300 | Q160: 5533 | R160: 4430 | S160: 6086.4395 | T160: 13290 | U160: 15216.099 | V160: =L160-H160 -> 64203.288
A161: 88 | B161: Dallas | C161: 2 | D161: Tier 2 | E161: 18 | F161: 24 | G161: 6 | H161: 443000 | I161: 27172.734 | J161: 9857.8199 | K161: 27172.734 | L161: 507203.29 | M161: 886 | N161: 3987 | O161: 360 | P161: 300 | Q161: 5533 | R161: 4430 | S161: 6086.4395 | T161: 13290 | U161: 15216.099 | V161: =L161-H161 -> 64203.288
A162: 102 | B162: Dallas | C162: 2 | D162: Tier 1 | E162: 19 | F162: 24 | G162: 5 | H162: 338000 | I162: 27642.992 | J162: 5568.9637 | K162: 27642.992 | L162: 398854.95 | M162: 563.33333 | N162: 2535 | O162: 300 | P162: 250 | Q162: 3648.3333 | R162: 3380 | S162: 4786.2594 | T162: 10140 | U162: 11965.648 | V162: =L162-H162 -> 60854.948
A163: 108 | B163: Dallas | C163: 2 | D163: Tier 2 | E163: 19 | F163: 24 | G163: 5 | H163: 443000 | I163: 27172.734 | J163: 8199.7468 | K163: 27172.734 | L163: 505545.21 | M163: 738.33333 | N163: 3322.5 | O163: 300 | P163: 250 | Q163: 4610.8333 | R163: 4430 | S163: 6066.5426 | T163: 13290 | U163: 15166.356 | V163: =L163-H163 -> 62545.215
A164: 120 | B164: Dallas | C164: 2 | D164: Tier 2 | E164: 19 | F164: 24 | G164: 5 | H164: 443000 | I164: 27172.734 | J164: 8199.7468 | K164: 27172.734 | L164: 505545.21 | M164: 738.33333 | N164: 3322.5 | O164: 300 | P164: 250 | Q164: 4610.8333 | R164: 4430 | S164: 6066.5426 | T164: 13290 | U164: 15166.356 | V164: =L164-H164 -> 62545.215
A165: 121 | B165: Dallas | C165: 2 | D165: Tier 3 | E165: 19 | F165: 24 | G165: 5 | H165: 676000 | I165: 34553.74 | J165: 13883.202 | K165: 34553.74 | L165: 758990.68 | M165: 1126.6667 | N165: 5070 | O165: 300 | P165: 250 | Q165: 6746.6667 | R165: 6760 | S165: 9107.8882 | T165: 20280 | U165: 22769.72 | V165: =L165-H165 -> 82990.682
A166: 126 | B166: Dallas | C166: 2 | D166: Tier 1 | E166: 20 | F166: 24 | G166: 4 | H166: 338000 | I166: 27642.992 | J166: 4447.8785 | K166: 27642.992 | L166: 397733.86 | M166: 450.66667 | N166: 2028 | O166: 240 | P166: 200 | Q166: 2918.6667 | R166: 3380 | S166: 4772.8063 | T166: 10140 | U166: 11932.016 | V166: =L166-H166 -> 59733.862
... A188: 89 | B188: Atlanta | C188: 2 | D188: Tier 1 | E188: 20 | F188: 24 | G188: 4 | H188: 305000 | I188: 30500 | J188: 3019.9984 | K188: 27450 | L188: 365970 | M188: 508.33333 | N188: 1118.3333 | O188: 200 | P188: 160 | Q188: 1986.6667 | R188: 3050 | S188: 3659.7 | T188: 9150 | U188: 10979.1 | V188: =L188-H188 -> 60969.998
V189: =SUM(V155:V188) -> 2202580.9
A190: 95 | B190: Dallas | C190: 2 | D190: Tier 3 | E190: 18 | F190: 25 | G190: 7 | H190: 676000 | I190: 34553.74 | J190: 19515.992 | K190: 34553.74 | L190: 764623.47 | M190: 1577.3333 | N190: 7098 | O190: 420 | P190: 350 | Q190: 9445.3333 | R190: 6760 | S190: 9175.4817 | T190: 20280 | U190: 22938.704 | V190: =L190-H190 -> 88623.472
A191: 107 | B191: Dallas | C191: 2 | D191: Tier 2 | E191: 19 | F191: 25 | G191: 6 | H191: 443000 | I191: 27172.734 | J191: 9857.8199 | K191: 27172.734 | L191: 507203.29 | M191: 886 | N191: 3987 | O191: 360 | P191: 300 | Q191: 5533 | R191: 4430 | S191: 6086.4395 | T191: 13290 | U191: 15216.099 | V191: =L191-H191 -> 64203.288
A192: 115 | B192: Dallas | C192: 2 | D192: Tier 2 | E192: 19 | F192: 25 | G192: 6 | H192: 443000 | I192: 27172.734 | J192: 9857.8199 | K192: 27172.734 | L192: 507203.29 | M192: 886 | N192: 3987 | O192: 360 | P192: 300 | Q192: 5533 | R192: 4430 | S192: 6086.4395 | T192: 13290 | U192: 15216.099 | V192: =L192-H192 -> 64203.288
A193: 116 | B193: Dallas | C193: 2 | D193: Tier 2 | E193: 19 | F193: 25 | G193: 6 | H193: 443000 | I193: 27172.734 | J193: 9857.8199 | K193: 27172.734 | L193: 507203.29 | M193: 886 | N193: 3987 | O193: 360 | P193: 300 | Q193: 5533 | R193: 4430 | S193: 6086.4395 | T193: 13290 | U193: 15216.099 | V193: =L193-H193 -> 64203.288
A194: 117 | B194: Dallas | C194: 2 | D194: Tier 2 | E194: 19 | F194: 25 | G194: 6 | H194: 443000 | I194: 27172.734 | J194: 9857.8199 | K194: 27172.734 | L194: 507203.29 | M194: 886 | N194: 3987 | O194: 360 | P194: 300 | Q194: 5533 | R194: 4430 | S194: 6086.4395 | T194: 13290 | U194: 15216.099 | V194: =L194-H194 -> 64203.288
A195: 118 | B195: Dallas | C195: 2 | D195: Tier 2 | E195: 19 | F195: 25 | G195: 6 | H195: 443000 | I195: 27172.734 | J195: 9857.8199 | K195: 27172.734 | L195: 507203.29 | M195: 886 | N195: 3987 | O195: 360 | P195: 300 | Q195: 5533 | R195: 4430 | S195: 6086.4395 | T195: 13290 | U195: 15216.099 | V195: =L195-H195 -> 64203.288
A196: 122 | B196: Dallas | C196: 2 | D196: Tier 3 | E196: 19 | F196: 25 | G196: 6 | H196: 676000 | I196: 34553.74 | J196: 16693.872 | K196: 34553.74 | L196: 761801.35 | M196: 1352 | N196: 6084 | O196: 360 | P196: 300 | Q196: 8096 | R196: 6760 | S196: 9141.6162 | T196: 20280 | U196: 22854.041 | V196: =L196-H196 -> 85801.352
A197: 123 | B197: Dallas | C197: 2 | D197: Tier 3 | E197: 19 | F197: 25 | G197: 6 | H197: 676000 | I197: 34553.74 | J197: 16693.872 | K197: 34553.74 | L197: 761801.35 | M197: 1352 | N197: 6084 | O197: 360 | P197: 300 | Q197: 8096 | R197: 6760 | S197: 9141.6162 | T197: 20280 | U197: 22854.041 | V197: =L197-H197 -> 85801.352
...

Sheet Assumptions
A1: Parameter | B1: Value | C1: Notes
A2: General
A3: Start_Year | B3: 2025 | C3: Base year for model
A4: Initial_Cash | B4: 500000000 | C4: Client capital available ($)
A5: Homes & Unit Economics
A6: Homes_Y1 | B6: 300 | C6: Number of homes bought & sold in Year 1
A7: Subscription Model | G7: =400*#REF!-B4 -> #REF!
A8: Sub_Start_Subscribers_Y1 | B8: 3000 | C8: Active subscribers in Year 1
A9: Sub_Monthly_Fee | B9: 25 | C9: Subscription price per month ($)
A10: Sub_Annual_Growth_Rate | B10: 1.5 | C10: YoY growth in subscribers (multiplier)
A11: Sub_Churn_Rate | B11: 0.1 | C11: Annual churn (for refinement)
A12: Operating Expenses
A13: Tax & Other
A14: Tax_Rate | B14: 0.21 | C14: Corporate tax rate (if applied later)
A15: office_dallas
A16: monthly rent | B16: =(E60+E61)/12 -> 6476 | C16: =B16*12 -> 77712
A17: Miscellaneous Expenses | B17: =1000 -> 1000 | C17: 4000 | D17: PACKERS AND MOVERS
C24: salary
A28: Role | B28: Count | C28: Salary (Annual) | D28: Monthly Cost (per person) | E28: Monthly Total Cost | F28: Notes
A29: Customer Support Reps | B29: 3 | C29: 50000 | D29: 12500 | E29: 37500 | F29: Handles all 3k subs
A30: Seller Advisors | B30: 2 | C30: 70000 | D30: 11666 | E30: 23332 | F30: Guides sellers
A31: Field Ops (Inspectors/Coordinators) | B31: 2 | C31: 60000 | D31: 10000 | E31: 20000 | F31: On-site coordination
A32: Marketing Specialist | B32: 2 | C32: 80000 | D32: 13333 | E32: 26666 | F32: Executes marketing
A33: Data/Valuation Analyst | B33: 1 | C33: 95000 | D33: 7916 | E33: 7916 | F33: Runs valuation models
A34: Product/Tech Lead | B34: 1 | C34: 120000 | D34: 10000 | E34: 10000 | F34: Single technical owner
A35: Partnerships Manager | B35: 1 | C35: 85000 | D35: 7083 | E35: 7083 | F35: Vendor + local onboarding
A36: Dallas General Manager | B36: 1 | C36: 150000 | D36: 12500 | E36: 12500 | F36: Runs entire metro
D37: TOTAL SALARY | E37: =SUM(E29:E36) -> 144997
C38: office cost
B41: Rate ($/sq ft/year) | C41: Monthly Rent (800 sq ft)
A42: Downtown Dallas | B42: 29 | C42: $1,933/month
A43: Uptown Dallas | B43: 44 | C43: $2,933/
A49: Expense Type | B49: Monthly Cost
A50: Electricity | B50: 200
A51: Internet | B51: 120
A52: Cleaning | B52: 150
A53: Water/Trash | B53: 50
A54: Office Supplies | B54: 75
A55: Insurance | B55: 60
A56: Furniture amortized | B56: 150
A57: Total Other Expenses (per office) | B57: $805/month
A59: Location | B59: Rent | C59: Other Expenses | D59: Total / Office / Month | E59: total year
A60: Downtown (Scenario B) | B60: 1933 | C60: 805 | D60: 2738 | E60: =D60*12 -> 32856
A61: Uptown (Scenario C) | B61: 2933 | C61: 805 | D61: 3738 | E61: =D61*12 -> 44856
C63: Marketing
A64: YEAR 1 MONTH-BY-MONTH MARKETING BREAKDOWN
A66: Month | B66: Digital Marketing Operations | C66: Pay-Per-Click (PPC) Management (15% of ad spend) | D66: SEO + Content Marketing | E66: Customer Review + Feedback Monitoring | F66: Monthly Ad Spend | H66: TOTAL | J66: Service | K66: Monthly Cost | L66: Notes
A67: Jan | B67: 25000 | C67: 15000 | D67: 10000 | E67: 3000 | F67: 100000 | H67: 153000 | J67: Digital Marketing Operations | K67: 25000 | L67: WebFX base retainer
A68: Feb | B68: 25000 | C68: 15000 | E68: 3000 | F68: 100000 | H68: 153000 | J68: Pay-Per-Click (PPC) Management (15% of ad spend) | K68: 15000 | L68: Based on $100K–$300K ad spend
A69: Mar | B69: 25000 | C69: 15000 | D69: 10000 | E69: 3000 | F69: 100000 | H69: 153000 | J69: SEO + Content Marketing | K69: 10000 | L69: Monthly SEO package
A70: Apr | B70: 25000 | C70: 15000 | D70: 10000 | E70: 3000 | F70: 100000 | H70: 153000 | J70: Customer Review + Feedback Monitoring | K70: 3000 | L70: Reputation management
A71: May | B71: 25000 | C71: 15000 | D71: 10000 | E71: 3000 | F71: 100000 | H71: 153000 | J71: Monthly Ad Spend | K71: 100000 | L71: Variable spend based on business needs
A72: Jun | B72: 25000 | C72: 15000 | D72: 10000 | E72: 3000 | F72: 100000 | H72: 153000 | J72: TOTAL MONTHLY COSTS (Recurring) | K72: 153000 | L72: Excludes one-time setup fees
A73: Jul | B73: 25000 | C73: 15000 | D73: 10000 | E73: 3000 | F73: 100000 | H73: 153000
A74: Aug | B74: 25000 | C74: 15000 | D74: 10000 | E74: 3000 | F74: 100000 | H74: 153000
A75: Sep | B75: 25000 | C75: 15000 | D75: 10000 | E75: 3000 | F75: 100000 | H75: 153000 | J75: Service | K75: Monthly Cost (Low) | L75: Notes
A76: Oct | B76: 25000 | C76: 15000 | D76: 10000 | E76: 3000 | F76: 100000 | H76: 153000 | J76: Digital Marketing Operations | K76: 40000 | L76: Increased workload across 2 metros
A77: Nov | B77: 25000 | C77: 15000 | D77: 10000 | E77: 3000 | F77: 100000 | H77: 153000 | J77: PPC Management (15% of ad spend) | K77: 30000 | L77: Based on $200K–$600K ad spend (combined or per metro)
A78: Dec | B78: 25000 | C78: 15000 | D78: 10000 | E78: 3000 | F78: 100000 | H78: 153000 | J78: SEO + Content Marketing | K78: 10000 | L78: Per month
J79: Customer Review + Feedback Monitoring | K79: 5000 | L79: Two-market coverage
G80: total | H80: =SUM(H67:H78) -> 1836000 | J80: Monthly Ad Spend | K80: 200000 | L80: Total across both markets
J81: TOTAL MONTHLY COSTS (Recurring) | K81: 285000 | L81: Excludes one-time setup
A82: EAR 2 MONTH-BY-MONTH MARKETING BREAKDOWN
A84: (Spending grows steadily but remains disciplined)
A86: Month | B86: Digital Marketing Operations | C86: Pay-Per-Click (PPC) Management (15% of ad spend) | D86: SEO + Content Marketing | E86: Customer Review + Feedback Monitoring | F86: Monthly Ad Spend | H86: TOTAL
A87: Jan | B87: 40000 | C87: 30000 | D87: 10000 | E87: 5000 | F87: 200000 | H87: 285000
A88: Feb | B88: 40000 | C88: 30000 | D88: 10000 | E88: 5000 | F88: 200000 | H88: 285000
A89: Mar | B89: 40000 | C89: 30000 | D89: 10000 | E89: 5000 | F89: 200000 | H89: 285000
A90: Apr | B90: 40000 | C90: 30000 | D90: 10000 | E90: 5000 | F90: 200000 | H90: 285000
A91: May | B91: 40000 | C91: 30000 | D91: 10000 | E91: 5000 | F91: 200000 | H91: 285000
A92: Jun | B92: 40000 | C92: 30000 | D92: 10000 | E92: 5000 | F92: 200000 | H92: 285000
A93: Jul | B93: 40000 | C93: 30000 | D93: 10000 | E93: 5000 | F93: 200000 | H93: 285000
A94: Aug | B94: 40000 | C94: 30000 | D94: 10000 | E94: 5000 | F94: 200000 | H94: 285000
A95: Sep | B95: 40000 | C95: 30000 | D95: 10000 | E95: 5000 | F95: 200000 | H95: 285000
A96: Oct | B96: 40000 | C96: 30000 | D96: 10000 | E96: 5000 | F96: 200000 | H96: 285000
A97: Nov | B97: 40000 | C97: 30000 | D97: 10000 | E97: 5000 | F97: 200000 | H97: 285000
A98: Dec | B98: 40000 | C98: 30000 | D98: 10000 | E98: 5000 | F98: 200000 | H98: 285000
C103: TECH
A107: YEAR 1 TOTAL (Platform Only)
A109: Component | B109: Cost
A110: Initial Build | B110: 150000
A111: Year 1 Maintenance | B111: 48000
A112: Total Year 1 Platform Cost | B112: 198000
A118: YEAR 2 TOTAL (Platform Only)
A120: Component | B120: Cost
A121: Enhancements | B121: 40000
A122: Year 2 Maintenance | B122: 60000
A123: Total Year 2 Platform Cost | B123: 130000
C126: LEAGAL FEE
A130: Legal Category | B130: Year 1 Cost (USD) | C130: Year 2 Cost (USD) | D130: Notes / Source Basis | E130: Legal Category | F130: Year 2 Cost (USD) | G130: Notes / Georgia-Specific Basis
A131: Business Formation & Corporate Governance | B131: 2200 | C131: 500 | D131: Formation + annual compliance (Texas SOS, IncFile, CBRE) | E131: Business Registration & Corporate Governance | F131: 600 | G131: Georgia SOS filing + annual compliance; similar to Texas but slightly higher attorney review time.
A132: Title / Lien / Property Dispute Support | B132: 18000 | C132: 18900 | D132: $600 per complex review × 30 (Texas title companies & attorney quotes) | E132: Title / Lien / Property Dispute Support | F132: 21000 | G132: GA title work is attorney-run; probate issues more common; $700 per complex review × 30 cases.
A133: Closing Attorney (optional) | B133: 9600 | C133: 9600 | D133: $400 × 24 closings; Texas title cost ranges | E133: Closing Attorney Fees (Mandatory) | F133: 18000 | G133: Georgia law requires an attorney for ALL closings. Estimated $1,000 × 18 closings (10% of 180 homes needing deeper attorney review).
A134: Subscription Product Legal (TOS, Privacy, Contracts) | B134: 5000 | C134: 2000 | D134: Standard SaaS pricing from privacy law firms (Osano, Termly, Iubenda, Dallas tech law firms) | E134: Subscription Product Legal (TOS, Privacy, SaaS) | F134: 2500 | G134: Slightly higher due to multi-state data compliance review; standard range from Osano/Termly/Iubenda.
A135: Employment & HR Legal | B135: 4000 | C135: 4200 | D135: Contract templates + EE agreements (Dallas HR attorneys) | E135: Employment & HR Legal | F135: 5000 | G135: Atlanta HR law firms charge $300–$450/hr; includes onboarding, contractor compliance, and multi-state HR alignment.
A136: Office Lease Legal (2 leases) | B136: 2000 | C136: 2000 | D136: $1,000 per lease review (LoopNet landlords + Dallas commercial attorneys) | E136: Office Lease Legal (Atlanta office) | F136: 2000 | G136: $1,000 per lease review; similar to Dallas.
A137: General Counsel Hours / Misc Legal | B137: 36000 | C137: 37800 | D137: Typical $250–$375/hr × ~10 hrs/mo startup use | E137: General Counsel Hours / Misc Legal | F137: 40000 | G137: Fractional GC support for multi-state operations; $3.3k/month average. Reflects added new-market legal overhead.
A138: TOTAL LEGAL FEES | B138: 112800 | C138: 112800
F139: =SUM(F131:F137) -> 89100 | G139: =89100/12 -> 7425
A141: Month | B141: Free Users (New) | C141: Paid Subs (New) | D141: Total Subs | E141: Revenue ($20/ user)
...

Sheet calculation_sheet
A1: Month | B1: Houses_Bought | C1: Houses_Sold | D1: Cumm_houses_bought | E1: Cumm_houses_sold | F1: Inventory | G1: Total_Buy_Price | H1: Total_Rehab_Cost | I1: Total_Buy_Txn_Cost | J1: Total_Holding_Cost | K1: Total_Sell_Txn_Cost | L1: Total_Service_Fees | M1: Total_Sale_Revenue | N1: Net_Cashflow | O1: Cumulative_Net_Cashflow
A2: 1 | B2: 10 | C2: 0 | D2: =SUM($B$2:B2) -> 10 | E2: =SUM($C$2:C2) -> 0 | F2: =E2-D2 -> -10 | G2: 4243000 | H2: 274860 | I2: =G2*0.01 -> 42430 | J2: 8878.8333 | K2: =M2*0.01 -> 0 | L2: =0.04*(G2+M2) -> 169720 | M2: 0 | N2: =(M2+L2)-(G2+H2+I2+J2+K2) -> -4399448.8 | O2: =SUM($N$2:N2) -> -4399448.8
A3: 2 | B3: 15 | C3: 0 | D3: =SUM($B$2:B3) -> 25 | E3: =SUM($C$2:C3) -> 0 | F3: =E3-D3 -> -25 | G3: 6586000 | H3: 415440 | I3: =G3*0.01 -> 65860 | J3: 22603.167 | K3: =M3*0.01 -> 0 | L3: =0.04*(G3+M3) -> 263440 | M3: 0 | N3: =(M3+L3)-(G3+H3+I3+J3+K3) -> -6826463.2 | O3: =SUM($N$2:N3) -> -11225912
A4: 3 | B4: 20 | C4: 0 | D4: =SUM($B$2:B4) -> 45 | E4: =SUM($C$2:C4) -> 0 | F4: =E4-D4 -> -45 | G4: 8824000 | H4: 556480 | I4: =G4*0.01 -> 88240 | J4: 40980.5 | K4: =M4*0.01 -> 0 | L4: =0.04*(G4+M4) -> 352960 | M4: 0 | N4: =(M4+L4)-(G4+H4+I4+J4+K4) -> -9156740.5 | O4: =SUM($N$2:N4) -> -20382652
A5: 4 | B5: 25 | C5: 0 | D5: =SUM($B$2:B5) -> 70 | E5: =SUM($C$2:C5) -> 0 | F5: =E5-D5 -> -70 | G5: 11062000 | H5: 697520 | I5: =G5*0.01 -> 110620 | J5: 64010.833 | K5: =M5*0.01 -> 0 | L5: =0.04*(G5+M5) -> 442480 | M5: 0 | N5: =(M5+L5)-(G5+H5+I5+J5+K5) -> -11491671 | O5: =SUM($N$2:N5) -> -31874323
A6: 5 | B6: 35 | C6: 2 | D6: =SUM($B$2:B6) -> 105 | E6: =SUM($C$2:C6) -> 2 | F6: =E6-D6 -> -103 | G6: 15410000 | H6: 971920 | I6: =G6*0.01 -> 154100 | J6: 94653.167 | K6: =M6*0.01 -> 7930.5576 | L6: =0.04*(G6+M6) -> 648122.23 | M6: 793055.76 | N6: =(M6+L6)-(G6+H6+I6+J6+K6) -> -15197426 | O6: =SUM($N$2:N6) -> -47071749
A7: 6 | B7: 40 | C7: 11 | D7: =SUM($B$2:B7) -> 145 | E7: =SUM($C$2:C7) -> 13 | F7: =E7-D7 -> -132 | G7: 17648000 | H7: 1112960 | I7: =G7*0.01 -> 176480 | J7: 122611.5 | K7: =M7*0.01 -> 47931.415 | L7: =0.04*(G7+M7) -> 897645.66 | M7: 4793141.5 | N7: =(M7+L7)-(G7+H7+I7+J7+K7) -> -13417196 | O7: =SUM($N$2:N7) -> -60488945
A8: 7 | B8: 40 | C8: 16 | D8: =SUM($B$2:B8) -> 185 | E8: =SUM($C$2:C8) -> 29 | F8: =E8-D8 -> -156 | G8: 17648000 | H8: 1112960 | I8: =G8*0.01 -> 176480 | J8: 145724.33 | K8: =M8*0.01 -> 74575.097 | L8: =0.04*(G8+M8) -> 1004220.4 | M8: 7457509.7 | N8: =(M8+L8)-(G8+H8+I8+J8+K8) -> -10696009 | O8: =SUM($N$2:N8) -> -71184954
A9: 8 | B9: 35 | C9: 27 | D9: =SUM($B$2:B9) -> 220 | E9: =SUM($C$2:C9) -> 56 | F9: =E9-D9 -> -164 | G9: 15410000 | H9: 971920 | I9: =G9*0.01 -> 154100 | J9: 152909.17 | K9: =M9*0.01 -> 137044.95 | L9: =0.04*(G9+M9) -> 1164579.8 | M9: 13704495 | N9: =(M9+L9)-(G9+H9+I9+J9+K9) -> -1956899.8 | O9: =SUM($N$2:N9) -> -73141854
A10: 9 | B10: 30 | C10: 27 | D10: =SUM($B$2:B10) -> 250 | E10: =SUM($C$2:C10) -> 83 | F10: =E10-D10 -> -167 | G10: 13067000 | H10: 831340 | I10: =G10*0.01 -> 130670 | J10: 156530 | K10: =M10*0.01 -> 129322.53 | L10: =0.04*(G10+M10) -> 1039970.1 | M10: 12932253 | N10: =(M10+L10)-(G10+H10+I10+J10+K10) -> -342639.68 | O10: =SUM($N$2:N10) -> -73484494
A11: 10 | B11: 25 | C11: 30 | D11: =SUM($B$2:B11) -> 275 | E11: =SUM($C$2:C11) -> 113 | F11: =E11-D11 -> -162 | G11: 11062000 | H11: 697520 | I11: =G11*0.01 -> 110620 | J11: 153501.33 | K11: =M11*0.01 -> 142765.59 | L11: =0.04*(G11+M11) -> 1013542.3 | M11: 14276559 | N11: =(M11+L11)-(G11+H11+I11+J11+K11) -> 3123694 | O11: =SUM($N$2:N11) -> -70360800
A12: 11 | B12: 15 | C12: 48 | D12: =SUM($B$2:B12) -> 290 | E12: =SUM($C$2:C12) -> 161 | F12: =E12-D12 -> -129 | G12: 6586000 | H12: 415440 | I12: =G12*0.01 -> 65860 | J12: 123948 | K12: =M12*0.01 -> 237140.37 | L12: =0.04*(G12+M12) -> 1212001.5 | M12: 23714037 | N12: =(M12+L12)-(G12+H12+I12+J12+K12) -> 17497650 | O12: =SUM($N$2:N12) -> -52863150
A13: 12 | B13: 10 | C13: 25 | D13: =SUM($B$2:B13) -> 300 | E13: =SUM($C$2:C13) -> 186 | F13: =E13-D13 -> -114 | G13: 4243000 | H13: 274860 | I13: =G13*0.01 -> 42430 | J13: 108557.17 | K13: =M13*0.01 -> 133931.8 | L13: =0.04*(G13+M13) -> 705447.22 | M13: 13393180 | N13: =(M13+L13)-(G13+H13+I13+J13+K13) -> 9295848.6 | O13: =SUM($N$2:N13) -> -43567301
A14: 13 | B14: 7 | C14: 30 | D14: =SUM($B$2:B14) -> 307 | E14: =SUM($C$2:C14) -> 216 | F14: =E14-D14 -> -91 | G14: 3124000 | H14: 198530.66 | I14: =G14*0.01 -> 31240 | J14: 86366.5 | K14: =M14*0.01 -> 158136.39 | L14: =0.0425*(G14+M14) -> 804849.66 | M14: 15813639 | N14: =(M14+L14)-(G14+H14+I14+J14+K14) -> 13020215 | O14: =SUM($N$2:N14) -> -30547086
A15: 14 | B15: 10 | C15: 24 | D15: =SUM($B$2:B15) -> 317 | E15: =SUM($C$2:C15) -> 240 | F15: =E15-D15 -> -77 | G15: 4243000 | H15: 280989.38 | I15: =G15*0.01 -> 42430 | J15: 73756.833 | K15: =M15*0.01 -> 118164.8 | L15: =0.0425*(G15+M15) -> 682527.89 | M15: 11816480 | N15: =(M15+L15)-(G15+H15+I15+J15+K15) -> 7740666.6 | O15: =SUM($N$2:N15) -> -22806419
A16: 15 | B16: 13 | C16: 30 | D16: =SUM($B$2:B16) -> 330 | E16: =SUM($C$2:C16) -> 270 | F16: =E16-D16 -> -60 | G16: 5700000 | H16: 370358.84 | I16: =G16*0.01 -> 57000 | J16: 57376 | K16: =M16*0.01 -> 155728.59 | L16: =0.0425*(G16+M16) -> 904096.52 | M16: 15572859 | N16: =(M16+L16)-(G16+H16+I16+J16+K16) -> 10136492 | O16: =SUM($N$2:N16) -> -12669927
A17: 16 | B17: 29 | C17: 14 | D17: =SUM($B$2:B17) -> 359 | E17: =SUM($C$2:C17) -> 284 | F17: =E17-D17 -> -75 | G17: 12085000 | H17: 869701.04 | I17: =G17*0.01 -> 120850 | J17: 66005.333 | K17: =M17*0.01 -> 78796.847 | L17: =0.0425*(G17+M17) -> 848499.1 | M17: 7879684.7 | N17: =(M17+L17)-(G17+H17+I17+J17+K17) -> -4492169.4 | O17: =SUM($N$2:N17) -> -17162096
A18: 17 | B18: 35 | C18: 14 | D18: =SUM($B$2:B18) -> 394 | E18: =SUM($C$2:C18) -> 298 | F18: =E18-D18 -> -96 | G18: 14533000 | H18: 1033678 | I18: =G18*0.01 -> 145330 | J18: 81214.5 | K18: =M18*0.01 -> 70489.75 | L18: =0.0425*(G18+M18) -> 917233.94 | M18: 7048975 | N18: =(M18+L18)-(G18+H18+I18+J18+K18) -> -7897503.3 | O18: =SUM($N$2:N18) -> -25059600
A19: 18 | B19: 51 | C19: 11 | D19: =SUM($B$2:B19) -> 445 | E19: =SUM($C$2:C19) -> 309 | F19: =E19-D19 -> -136 | G19: 21018000 | H19: 1534920.2 | I19: =G19*0.01 -> 210180 | J19: 110114.33 | K19: =M19*0.01 -> 56418.992 | L19: =0.0425*(G19+M19) -> 1133045.7 | M19: 5641899.2 | N19: =(M19+L19)-(G19+H19+I19+J19+K19) -> -16154689 | O19: =SUM($N$2:N19) -> -41214288
A20: 19 | B20: 54 | C20: 12 | D20: =SUM($B$2:B20) -> 499 | E20: =SUM($C$2:C20) -> 321 | F20: =E20-D20 -> -178 | G20: 22358000 | H20: 1635620.2 | I20: =G20*0.01 -> 223580 | J20: 140768.33 | K20: =M20*0.01 -> 57782.128 | L20: =0.0425*(G20+M20) -> 1195789 | M20: 5778212.8 | N20: =(M20+L20)-(G20+H20+I20+J20+K20) -> -17441749 | O20: =SUM($N$2:N20) -> -58656037
A21: 20 | B21: 53 | C21: 10 | D21: =SUM($B$2:B21) -> 552 | E21: =SUM($C$2:C21) -> 331 | F21: =E21-D21 -> -221 | G21: 21473000 | H21: 1612478 | I21: =G21*0.01 -> 214730 | J21: 170154.5 | K21: =M21*0.01 -> 52467.532 | L21: =0.0425*(G21+M21) -> 1135589.5 | M21: 5246753.2 | N21: =(M21+L21)-(G21+H21+I21+J21+K21) -> -17140487 | O21: =SUM($N$2:N21) -> -75796524
A22: 21 | B22: 50 | C22: 25 | D22: =SUM($B$2:B22) -> 602 | E22: =SUM($C$2:C22) -> 356 | F22: =E22-D22 -> -246 | G22: 20249000 | H22: 1530489.5 | I22: =G22*0.01 -> 202490 | J22: 187561.5 | K22: =M22*0.01 -> 110545.59 | L22: =0.0425*(G22+M22) -> 1330401.3 | M22: 11054559 | N22: =(M22+L22)-(G22+H22+I22+J22+K22) -> -9895125.9 | O22: =SUM($N$2:N22) -> -85691650
A23: 22 | B23: 34 | C23: 33 | D23: =SUM($B$2:B23) -> 636 | E23: =SUM($C$2:C23) -> 389 | F23: =E23-D23 -> -247 | G23: 13864000 | H23: 1031147.3 | I23: =G23*0.01 -> 138640 | J23: 185716.5 | K23: =M23*0.01 -> 160260.25 | L23: =0.0425*(G23+M23) -> 1270326 | M23: 16026025 | N23: =(M23+L23)-(G23+H23+I23+J23+K23) -> 1916586.5 | O23: =SUM($N$2:N23) -> -83775064
A24: 23 | B24: 25 | C24: 57 | D24: =SUM($B$2:B24) -> 661 | E24: =SUM($C$2:C24) -> 446 | F24: =E24-D24 -> -215 | G24: 9843000 | H24: 759089.38 | I24: =G24*0.01 -> 98430 | J24: 160155.67 | K24: =M24*0.01 -> 265074.69 | L24: =0.0425*(G24+M24) -> 1544894.9 | M24: 26507469 | N24: =(M24+L24)-(G24+H24+I24+J24+K24) -> 16926614 | O24: =SUM($N$2:N24) -> -66848449
A25: 24 | B25: 19 | C25: 34 | D25: =SUM($B$2:B25) -> 680 | E25: =SUM($C$2:C25) -> 480 | F25: =E25-D25 -> -200 | G25: 7609000 | H25: 581330.66 | I25: =G25*0.01 -> 76090 | J25: 147690.5 | K25: =M25*0.01 -> 161075.81 | L25: =0.0425*(G25+M25) -> 1007954.7 | M25: 16107581 | N25: =(M25+L25)-(G25+H25+I25+J25+K25) -> 8540348.6 | O25: =SUM($N$2:N25) -> -58308101
... A34: 33 | B34: 0 | C34: 1 | D34: =SUM($B$2:B34) -> 680 | E34: =SUM($C$2:C34) -> 680 | F34: =E34-D34 -> 0 | G34: 0 | H34: 0 | I34: =G34*0.01 -> 0 | J34: 0 | K34: =M34*0.01 -> 7244.0704 | L34: =0.0425*(G34+M34) -> 30787.299 | M34: 724407.04 | N34: =(M34+L34)-(G34+H34+I34+J34+K34) -> 747950.27 | O34: =SUM($N$2:N34) -> 41163990

Sheet operation_exp
A1: Marketing | B1: Office | C1: Salary | D1: tech_maintain | E1: SubSCRIPTION_revenue | F1: legal_expense | G1: Miscexp | H1: Total_expense | I1: Final_Net_Cashflow | J1: Cumulative_Final_Net_Cashflow
A2: 153000 | B2: =Assumptions!B16 -> 6476 | C2: 144997 | D2: =48000/12 -> 4000 | E2: =Assumptions!E142 -> 400 | F2: =Assumptions!$C$138/12 -> 9400 | G2: 20000 | H2: =B2+D2+F2-E2+G2 -> 39476 | I2: =calculation_sheet!N2-operation_exp!H2 -> -4438924.8 | J2: =I2-Assumptions!B110 -> -4588924.8
A3: 153000 | B3: 6476 | C3: 144997 | D3: =48000/12 -> 4000 | E3: =Assumptions!E143 -> 900 | F3: =Assumptions!$C$138/12 -> 9400 | G3: 20000 | H3: =B3+D3+F3-E3+G3+Balance_Sheet!E2 -> 340973 | I3: =calculation_sheet!N3-operation_exp!H3 -> -7167436.2 | J3: =J2+I3 -> -11756361
A4: 153000 | B4: 6476 | C4: 144997 | D4: =48000/12 -> 4000 | E4: =Assumptions!E144 -> 1460 | F4: =Assumptions!$C$138/12 -> 9400 | G4: 20000 | H4: =B4+D4+F4-E4+G4+Balance_Sheet!E3 -> 340413 | I4: =calculation_sheet!N4-operation_exp!H4 -> -9497153.5 | J4: =J3+I4 -> -21253514
A5: 153000 | B5: 6476 | C5: 144997 | D5: =48000/12 -> 4000 | E5: =Assumptions!E145 -> 2220 | F5: =Assumptions!$C$138/12 -> 9400 | G5: 35000 | H5: =B5+D5+F5-E5+G5+Balance_Sheet!E4 -> 354653 | I5: =calculation_sheet!N5-operation_exp!H5 -> -11846324 | J5: =J4+I5 -> -33099838
A6: 153000 | B6: 6476 | C6: 144997 | D6: =48000/12 -> 4000 | E6: =Assumptions!E146 -> 3140 | F6: =Assumptions!$C$138/12 -> 9400 | G6: 35000 | H6: =B6+D6+F6-E6+G6+Balance_Sheet!E5 -> 353733 | I6: =calculation_sheet!N6-operation_exp!H6 -> -15551159 | J6: =J5+I6 -> -48650997
A7: 153000 | B7: 6476 | C7: 144997 | D7: =48000/12 -> 4000 | E7: =Assumptions!E147 -> 4120 | F7: =Assumptions!$C$138/12 -> 9400 | G7: 35000 | H7: =B7+D7+F7-E7+G7+Balance_Sheet!E6 -> 352753 | I7: =calculation_sheet!N7-operation_exp!H7 -> -13769949 | J7: =J6+I7 -> -62420946
A8: 153000 | B8: 6476 | C8: 144997 | D8: =48000/12 -> 4000 | E8: =Assumptions!E148 -> 5060 | F8: =Assumptions!$C$138/12 -> 9400 | G8: 35000 | H8: =B8+D8+F8-E8+G8+Balance_Sheet!E7 -> 351813 | I8: =calculation_sheet!N8-operation_exp!H8 -> -11047822 | J8: =J7+I8 -> -73468768
A9: 153000 | B9: 6476 | C9: 144997 | D9: =48000/12 -> 4000 | E9: =Assumptions!E149 -> 5900 | F9: =Assumptions!$C$138/12 -> 9400 | G9: 50000 | H9: =B9+D9+F9-E9+G9+Balance_Sheet!E8 -> 365973 | I9: =calculation_sheet!N9-operation_exp!H9 -> -2322872.8 | J9: =J8+I9 -> -75791641
A10: 153000 | B10: 6476 | C10: 144997 | D10: =48000/12 -> 4000 | E10: =Assumptions!E150 -> 6600 | F10: =Assumptions!$C$138/12 -> 9400 | G10: 50000 | H10: =B10+D10+F10-E10+G10+Balance_Sheet!E9 -> 365273 | I10: =calculation_sheet!N10-operation_exp!H10 -> -707912.68 | J10: =J9+I10 -> -76499554
A11: 153000 | B11: 6476 | C11: 144997 | D11: =48000/12 -> 4000 | E11: =Assumptions!E151 -> 7240 | F11: =Assumptions!$C$138/12 -> 9400 | G11: 50000 | H11: =B11+D11+F11-E11+G11+Balance_Sheet!E10 -> 364633 | I11: =calculation_sheet!N11-operation_exp!H11 -> 2759061 | J11: =J10+I11 -> -73740493
A12: 153000 | B12: 6476 | C12: 144997 | D12: =48000/12 -> 4000 | E12: =Assumptions!E152 -> 7540 | F12: =Assumptions!$C$138/12 -> 9400 | G12: 50000 | H12: =B12+D12+F12-E12+G12+Balance_Sheet!E11 -> 364333 | I12: =calculation_sheet!N12-operation_exp!H12 -> 17133317 | J12: =J11+I12 -> -56607176
A13: 285000 | B13: 6476 | C13: 144997 | D13: =60000/12 -> 5000 | E13: =Assumptions!E153 -> 7920 | F13: =Assumptions!$C$138/12 -> 9400 | G13: 60000 | H13: =B13+D13+F13-E13+G13+Balance_Sheet!E12 -> 374953 | I13: =calculation_sheet!N13-operation_exp!H13 -> 8920895.6 | J13: =J12+I13-Assumptions!B121 -> -47726280
A14: 285000 | B14: 6476 | C14: 144997 | D14: =60000/12 -> 5000 | E14: =Assumptions!$F$169 -> 20920 | F14: =Assumptions!$C$138/12 -> 9400 | G14: 60000 | H14: =B14+D14+F14-E14+G14+Balance_Sheet!E13 -> 493953 | I14: =calculation_sheet!N14-operation_exp!H14 -> 12526262 | J14: =J13+I14 -> -35200018
A15: 285000 | B15: 6476 | C15: 144997 | D15: =60000/12 -> 5000 | E15: =Assumptions!$F$169 -> 20920 | F15: =Assumptions!$C$138/12+Assumptions!$F$139/12 -> 16825 | G15: 60000 | H15: =B15+D15+F15-E15+G15+Balance_Sheet!E14 -> 501378 | I15: =calculation_sheet!N15-operation_exp!H15 -> 7239288.6 | J15: =J14+I15 -> -27960729
A16: 285000 | B16: =6476*2 -> 12952 | C16: =144997*1.4 -> 202995.8 | D16: =60000/12 -> 5000 | E16: =Assumptions!$F$169 -> 20920 | F16: =Assumptions!$C$138/12+Assumptions!$F$139/12 -> 16825 | G16: 60000 | H16: =B16+D16+F16-E16+G16+Balance_Sheet!E15 -> 507854 | I16: =calculation_sheet!N16-operation_exp!H16 -> 9628638.4 | J16: =J15+I16 -> -18332091
A17: 285000 | B17: =6476*2 -> 12952 | C17: =144997*1.4 -> 202995.8 | D17: =60000/12 -> 5000 | E17: =Assumptions!$F$169 -> 20920 | F17: =Assumptions!$C$138/12+Assumptions!$F$139/12 -> 16825 | G17: 80000 | H17: =B17+D17+F17-E17+G17+Balance_Sheet!E16 -> 585852.8 | I17: =calculation_sheet!N17-operation_exp!H17 -> -5078022.2 | J17: =J16+I17 -> -23410113
A18: 285000 | B18: =6476*2 -> 12952 | C18: =144997*1.4 -> 202995.8 | D18: =60000/12 -> 5000 | E18: =Assumptions!$F$169 -> 20920 | F18: =Assumptions!$C$138/12+Assumptions!$F$139/12 -> 16825 | G18: 80000 | H18: =B18+D18+F18-E18+G18+Balance_Sheet!E17 -> 585852.8 | I18: =calculation_sheet!N18-operation_exp!H18 -> -8483356.1 | J18: =J17+I18 -> -31893469
A19: 285000 | B19: =6476*2 -> 12952 | C19: =144997*1.4 -> 202995.8 | D19: =60000/12 -> 5000 | E19: =Assumptions!$F$169 -> 20920 | F19: =Assumptions!$C$138/12+Assumptions!$F$139/12 -> 16825 | G19: 80000 | H19: =B19+D19+F19-E19+G19+Balance_Sheet!E18 -> 585852.8 | I19: =calculation_sheet!N19-operation_exp!H19 -> -16740541 | J19: =J18+I19 -> -48634011
A20: 285000 | B20: =6476*2 -> 12952 | C20: =144997*1.4 -> 202995.8 | D20: =60000/12 -> 5000 | E20: =Assumptions!$F$169 -> 20920 | F20: =Assumptions!$C$138/12+Assumptions!$F$139/12 -> 16825 | G20: 80000 | H20: =B20+D20+F20-E20+G20+Balance_Sheet!E19 -> 585852.8 | I20: =calculation_sheet!N20-operation_exp!H20 -> -18027602 | J20: =J19+I20 -> -66661612
A21: 285000 | B21: =6476*2 -> 12952 | C21: =144997*1.4 -> 202995.8 | D21: =60000/12 -> 5000 | E21: =Assumptions!$F$169 -> 20920 | F21: =Assumptions!$C$138/12+Assumptions!$F$139/12 -> 16825 | G21: 80000 | H21: =B21+D21+F21-E21+G21+Balance_Sheet!E20 -> 585852.8 | I21: =calculation_sheet!N21-operation_exp!H21 -> -17726340 | J21: =J20+I21 -> -84387952
A22: 285000 | B22: =6476*2 -> 12952 | C22: =144997*1.4 -> 202995.8 | D22: =60000/12 -> 5000 | E22: =Assumptions!$F$169 -> 20920 | F22: =Assumptions!$C$138/12+Assumptions!$F$139/12 -> 16825 | G22: 80000 | H22: =B22+D22+F22-E22+G22+Balance_Sheet!E21 -> 585852.8 | I22: =calculation_sheet!N22-operation_exp!H22 -> -10480979 | J22: =J21+I22 -> -94868931
A23: 285000 | B23: =6476*2 -> 12952 | C23: =144997*1.4 -> 202995.8 | D23: =60000/12 -> 5000 | E23: =Assumptions!$F$169 -> 20920 | F23: =Assumptions!$C$138/12+Assumptions!$F$139/12 -> 16825 | G23: 80000 | H23: =B23+D23+F23-E23+G23+Balance_Sheet!E22 -> 585852.8 | I23: =calculation_sheet!N23-operation_exp!H23 -> 1330733.7 | J23: =J22+I23 -> -93538197
A24: 285000 | B24: =6476*2 -> 12952 | C24: =144997*1.4 -> 202995.8 | D24: =60000/12 -> 5000 | E24: =Assumptions!$F$169 -> 20920 | F24: =Assumptions!$C$138/12+Assumptions!$F$139/12 -> 16825 | G24: 80000 | H24: =B24+D24+F24-E24+G24+Balance_Sheet!E23 -> 585852.8 | I24: =calculation_sheet!N24-operation_exp!H24 -> 16340762 | J24: =J23+I24 -> -77197436
A25: 285000 | B25: =6476*2 -> 12952 | C25: =144997*1.4 -> 202995.8 | D25: =60000/12 -> 5000 | E25: =Assumptions!$F$169 -> 20920 | F25: =Assumptions!$C$138/12+Assumptions!$F$139/12 -> 16825 | G25: 80000 | H25: =B25+D25+F25-E25+G25+Balance_Sheet!E24 -> 585852.8 | I25: =calculation_sheet!N25-operation_exp!H25 -> 7954495.8 | J25: =J24+I25 -> -69242940
A26: 285000 | B26: =6476*2 -> 12952 | C26: =144997*1.4 -> 202995.8 | D26: =60000/12 -> 5000 | E26: =Assumptions!$F$169 -> 20920 | F26: =Assumptions!$C$138/12+Assumptions!$F$139/12 -> 16825 | G26: 100000 | H26: =B26+D26+F26-E26+G26+Balance_Sheet!E25 -> 605852.8 | I26: =calculation_sheet!N26-operation_exp!H26 -> 21637226 | J26: =J25+I26 -> -47605714
A27: 285000 | B27: =6476*2 -> 12952 | C27: =144997*1.4 -> 202995.8 | D27: =60000/12 -> 5000 | E27: =Assumptions!$F$169 -> 20920 | F27: =Assumptions!$C$138/12+Assumptions!$F$139/12 -> 16825 | G27: 100000 | H27: =B27+D27+F27-E27+G27+Balance_Sheet!E26 -> 605852.8 | I27: =calculation_sheet!N27-operation_exp!H27 -> 18651507 | J27: =J26+I27 -> -28954207
... A34: 285000 | B34: =6476*2 -> 12952 | C34: =144997*1.4 -> 202995.8 | D34: =60000/12 -> 5000 | E34: =Assumptions!$F$169 -> 20920 | F34: =Assumptions!$C$138/12+Assumptions!$F$139/12 -> 16825 | G34: 100000 | H34: =B34+D34+F34-E34+G34+Balance_Sheet!E33 -> 605852.8 | I34: =calculation_sheet!N34-operation_exp!H34 -> 142097.47 | J34: =J33+I34 -> 24776476

Sheet final_phase1_full_costs
A1: House_ID | B1: Market | C1: Phase | D1: Tier | E1: Buy_Month | F1: Sell_Month | G1: Holding_Period | H1: Buy_Price | I1: Rehab_Cost | J1: Appreciation_Gain | K1: Uplift_Gain | L1: Sell_Price | M1: Insurance_Cost | N1: Property_Tax_Cost | O1: Maintenance_Cost | P1: HOA_Cost | Q1: Total_Holding_Cost | R1: Buy_Txn_Cost | S1: Sell_Txn_Cost | T1: Service_Fee_Buy | U1: Service_Fee_Sell | V1: Profit
A2: 1 | B2: Dallas | C2: 1 | D2: Tier 1 | E2: 1 | F2: 5 | G2: 4 | H2: 338000 | I2: 27040 | J2: 4447.8785 | K2: 27040 | L2: 396527.88 | M2: 450.66667 | N2: 2028 | O2: 240 | P2: 200 | Q2: 2918.6667 | R2: 3380 | S2: 4758.3345 | T2: 10140 | U2: 11895.836 | V2: =L2-H2 -> 58527.878
A3: 4 | B3: Dallas | C3: 1 | D3: Tier 1 | E3: 1 | F3: 5 | G3: 4 | H3: 338000 | I3: 27040 | J3: 4447.8785 | K3: 27040 | L3: 396527.88 | M3: 450.66667 | N3: 2028 | O3: 240 | P3: 200 | Q3: 2918.6667 | R3: 3380 | S3: 4758.3345 | T3: 10140 | U3: 11895.836 | V3: =L3-H3 -> 58527.878 | Z3: Months | AA3: total price
V4: =SUM(V2:V3) -> 117055.76 | Z4: 5 | AA4: =SUMIF(F2:F314,Z4,H2:H314) -> 676000
A5: 2 | B5: Dallas | C5: 1 | D5: Tier 1 | E5: 1 | F5: 6 | G5: 5 | H5: 338000 | I5: 27040 | J5: 5568.9637 | K5: 27040 | L5: 397648.96 | M5: 563.33333 | N5: 2535 | O5: 300 | P5: 250 | Q5: 3648.3333 | R5: 3380 | S5: 4771.7876 | T5: 10140 | U5: 11929.469 | V5: =L5-H5 -> 59648.964 | Z5: 6 | AA5: =SUMIF(F3:F315,Z5,H3:H315) -> 4138000
A6: 3 | B6: Dallas | C6: 1 | D6: Tier 1 | E6: 1 | F6: 6 | G6: 5 | H6: 338000 | I6: 27040 | J6: 5568.9637 | K6: 27040 | L6: 397648.96 | M6: 563.33333 | N6: 2535 | O6: 300 | P6: 250 | Q6: 3648.3333 | R6: 3380 | S6: 4771.7876 | T6: 10140 | U6: 11929.469 | V6: =L6-H6 -> 59648.964 | Z6: 7 | AA6: =SUMIF(F4:F316,Z6,H4:H316) -> 6481000
A7: 6 | B7: Dallas | C7: 1 | D7: Tier 2 | E7: 1 | F7: 6 | G7: 5 | H7: 443000 | I7: 26580 | J7: 8199.7468 | K7: 26580 | L7: 504359.75 | M7: 738.33333 | N7: 3322.5 | O7: 300 | P7: 250 | Q7: 4610.8333 | R7: 4430 | S7: 6052.317 | T7: 13290 | U7: 15130.792 | V7: =L7-H7 -> 61359.747 | Z7: 8 | AA7: =SUMIF(F5:F317,Z7,H5:H317) -> 11971000
A8: 7 | B8: Dallas | C8: 1 | D8: Tier 2 | E8: 1 | F8: 6 | G8: 5 | H8: 443000 | I8: 26580 | J8: 8199.7468 | K8: 26580 | L8: 504359.75 | M8: 738.33333 | N8: 3322.5 | O8: 300 | P8: 250 | Q8: 4610.8333 | R8: 4430 | S8: 6052.317 | T8: 13290 | U8: 15130.792 | V8: =L8-H8 -> 61359.747 | Z8: 9 | AA8: =SUMIF(F6:F318,Z8,H6:H318) -> 11272000
A9: 8 | B9: Dallas | C9: 1 | D9: Tier 2 | E9: 1 | F9: 6 | G9: 5 | H9: 443000 | I9: 26580 | J9: 8199.7468 | K9: 26580 | L9: 504359.75 | M9: 738.33333 | N9: 3322.5 | O9: 300 | P9: 250 | Q9: 4610.8333 | R9: 4430 | S9: 6052.317 | T9: 13290 | U9: 15130.792 | V9: =L9-H9 -> 61359.747 | Z9: 10 | AA9: =SUMIF(F7:F319,Z9,H7:H319) -> 12414000
A10: 9 | B10: Dallas | C10: 1 | D10: Tier 2 | E10: 1 | F10: 6 | G10: 5 | H10: 443000 | I10: 26580 | J10: 8199.7468 | K10: 26580 | L10: 504359.75 | M10: 738.33333 | N10: 3322.5 | O10: 300 | P10: 250 | Q10: 4610.8333 | R10: 4430 | S10: 6052.317 | T10: 13290 | U10: 15130.792 | V10: =L10-H10 -> 61359.747 | Z10: =Z9+1 -> 11 | AA10: =SUMIF(F8:F320,Z10,H8:H320) -> 20726000
A11: 11 | B11: Dallas | C11: 1 | D11: Tier 1 | E11: 2 | F11: 6 | G11: 4 | H11: 338000 | I11: 27040 | J11: 4447.8785 | K11: 27040 | L11: 396527.88 | M11: 450.66667 | N11: 2028 | O11: 240 | P11: 200 | Q11: 2918.6667 | R11: 3380 | S11: 4758.3345 | T11: 10140 | U11: 11895.836 | V11: =L11-H11 -> 58527.878 | Z11: =Z10+1 -> 12 | AA11: =SUMIF(F9:F321,Z11,H9:H321) -> 11738000
A12: 13 | B12: Dallas | C12: 1 | D12: Tier 1 | E12: 2 | F12: 6 | G12: 4 | H12: 338000 | I12: 27040 | J12: 4447.8785 | K12: 27040 | L12: 396527.88 | M12: 450.66667 | N12: 2028 | O12: 240 | P12: 200 | Q12: 2918.6667 | R12: 3380 | S12: 4758.3345 | T12: 10140 | U12: 11895.836 | V12: =L12-H12 -> 58527.878 | Z12: =Z11+1 -> 13 | AA12: =SUMIF(F10:F322,Z12,H10:H322) -> 13848000
A13: 15 | B13: Dallas | C13: 1 | D13: Tier 1 | E13: 2 | F13: 6 | G13: 4 | H13: 338000 | I13: 27040 | J13: 4447.8785 | K13: 27040 | L13: 396527.88 | M13: 450.66667 | N13: 2028 | O13: 240 | P13: 200 | Q13: 2918.6667 | R13: 3380 | S13: 4758.3345 | T13: 10140 | U13: 11895.836 | V13: =L13-H13 -> 58527.878 | Z13: =Z12+1 -> 14 | AA13: =SUMIF(F11:F323,Z13,H11:H323) -> 10281000
A14: 28 | B14: Dallas | C14: 1 | D14: Tier 1 | E14: 3 | F14: 6 | G14: 3 | H14: 338000 | I14: 27040 | J14: 3330.4514 | K14: 27040 | L14: 395410.45 | M14: 338 | N14: 1521 | O14: 180 | P14: 150 | Q14: 2189 | R14: 3380 | S14: 4744.9254 | T14: 10140 | U14: 11862.314 | V14: =L14-H14 -> 57410.451 | Z14: =Z13+1 -> 15 | AA14: =SUMIF(F12:F324,Z14,H12:H324) -> 13615000
A15: 31 | B15: Dallas | C15: 1 | D15: Tier 1 | E15: 3 | F15: 6 | G15: 3 | H15: 338000 | I15: 27040 | J15: 3330.4514 | K15: 27040 | L15: 395410.45 | M15: 338 | N15: 1521 | O15: 180 | P15: 150 | Q15: 2189 | R15: 3380 | S15: 4744.9254 | T15: 10140 | U15: 11862.314 | V15: =L15-H15 -> 57410.451 | Z15: =Z14+1 -> 16 | AA15: =SUMIF(F13:F325,Z15,H13:H325) -> 6924000
V16: =SUM(V5:V15) -> 655141.45 | Z16: =Z15+1 -> 17 | AA16: =SUMIF(F14:F326,Z16,H14:H326)+SUM(final_phase2_full_costs!H2:H3) -> 6143000
A17: 5 | B17: Dallas | C17: 1 | D17: Tier 2 | E17: 1 | F17: 7 | G17: 6 | H17: 443000 | I17: 26580 | J17: 9857.8199 | K17: 26580 | L17: 506017.82 | M17: 886 | N17: 3987 | O17: 360 | P17: 300 | Q17: 5533 | R17: 4430 | S17: 6072.2138 | T17: 13290 | U17: 15180.535 | V17: =L17-H17 -> 63017.82 | Z17: =Z16+1 -> 18 | AA17: =SUMIF(F15:F327,Z17,H15:H327)+SUM(final_phase2_full_costs!H5:H11) -> 4919000
A18: 10 | B18: Dallas | C18: 1 | D18: Tier 3 | E18: 1 | F18: 7 | G18: 6 | H18: 676000 | I18: 33800 | J18: 16693.872 | K18: 33800 | L18: 760293.87 | M18: 1352 | N18: 6084 | O18: 360 | P18: 300 | Q18: 8096 | R18: 6760 | S18: 9123.5265 | T18: 20280 | U18: 22808.816 | V18: =L18-H18 -> 84293.872 | Z18: =Z17+1 -> 19 | AA18: =SUMIF(final_phase2_full_costs!F2:F397,Z18,final_phase2_full_costs!H2:H397) -> 5024000
A19: 12 | B19: Dallas | C19: 1 | D19: Tier 1 | E19: 2 | F19: 7 | G19: 5 | H19: 338000 | I19: 27040 | J19: 5568.9637 | K19: 27040 | L19: 397648.96 | M19: 563.33333 | N19: 2535 | O19: 300 | P19: 250 | Q19: 3648.3333 | R19: 3380 | S19: 4771.7876 | T19: 10140 | U19: 11929.469 | V19: =L19-H19 -> 59648.964 | Z19: =Z18+1 -> 20 | AA19: =SUMIF(final_phase2_full_costs!F3:F398,Z19,final_phase2_full_costs!H3:H398) -> 4581000
A20: 14 | B20: Dallas | C20: 1 | D20: Tier 1 | E20: 2 | F20: 7 | G20: 5 | H20: 338000 | I20: 27040 | J20: 5568.9637 | K20: 27040 | L20: 397648.96 | M20: 563.33333 | N20: 2535 | O20: 300 | P20: 250 | Q20: 3648.3333 | R20: 3380 | S20: 4771.7876 | T20: 10140 | U20: 11929.469 | V20: =L20-H20 -> 59648.964 | Z20: =Z19+1 -> 21 | AA20: =SUMIF(final_phase2_full_costs!F4:F399,Z20,final_phase2_full_costs!H4:H399) -> 9497000
A21: 16 | B21: Dallas | C21: 1 | D21: Tier 2 | E21: 2 | F21: 7 | G21: 5 | H21: 443000 | I21: 26580 | J21: 8199.7468 | K21: 26580 | L21: 504359.75 | M21: 738.33333 | N21: 3322.5 | O21: 300 | P21: 250 | Q21: 4610.8333 | R21: 4430 | S21: 6052.317 | T21: 13290 | U21: 15130.792 | V21: =L21-H21 -> 61359.747 | Z21: =Z20+1 -> 22 | AA21: =SUMIF(final_phase2_full_costs!F5:F400,Z21,final_phase2_full_costs!H5:H400) -> 13864000
A22: 21 | B22: Dallas | C22: 1 | D22: Tier 2 | E22: 2 | F22: 7 | G22: 5 | H22: 443000 | I22: 26580 | J22: 8199.7468 | K22: 26580 | L22: 504359.75 | M22: 738.33333 | N22: 3322.5 | O22: 300 | P22: 250 | Q22: 4610.8333 | R22: 4430 | S22: 6052.317 | T22: 13290 | U22: 15130.792 | V22: =L22-H22 -> 61359.747 | Z22: =Z21+1 -> 23 | AA22: =SUMIF(final_phase2_full_costs!F6:F401,Z22,final_phase2_full_costs!H6:H401) -> 22828000
A23: 23 | B23: Dallas | C23: 1 | D23: Tier 2 | E23: 2 | F23: 7 | G23: 5 | H23: 443000 | I23: 26580 | J23: 8199.7468 | K23: 26580 | L23: 504359.75 | M23: 738.33333 | N23: 3322.5 | O23: 300 | P23: 250 | Q23: 4610.8333 | R23: 4430 | S23: 6052.317 | T23: 13290 | U23: 15130.792 | V23: =L23-H23 -> 61359.747 | Z23: =Z22+1 -> 24 | AA23: =SUMIF(final_phase2_full_costs!F7:F402,Z23,final_phase2_full_costs!H7:H402) -> 13905000
A24: 29 | B24: Dallas | C24: 1 | D24: Tier 1 | E24: 3 | F24: 7 | G24: 4 | H24: 338000 | I24: 27040 | J24: 4447.8785 | K24: 27040 | L24: 396527.88 | M24: 450.66667 | N24: 2028 | O24: 240 | P24: 200 | Q24: 2918.6667 | R24: 3380 | S24: 4758.3345 | T24: 10140 | U24: 11895.836 | V24: =L24-H24 -> 58527.878 | Z24: =Z23+1 -> 25 | AA24: =SUMIF(final_phase2_full_costs!F8:F403,Z24,final_phase2_full_costs!H8:H403) -> 18627000
A25: 32 | B25: Dallas | C25: 1 | D25: Tier 1 | E25: 3 | F25: 7 | G25: 4 | H25: 338000 | I25: 27040 | J25: 4447.8785 | K25: 27040 | L25: 396527.88 | M25: 450.66667 | N25: 2028 | O25: 240 | P25: 200 | Q25: 2918.6667 | R25: 3380 | S25: 4758.3345 | T25: 10140 | U25: 11895.836 | V25: =L25-H25 -> 58527.878 | Z25: =Z24+1 -> 26 | AA25: =SUMIF(final_phase2_full_costs!F9:F404,Z25,final_phase2_full_costs!H9:H404) -> 16004000
A26: 36 | B26: Dallas | C26: 1 | D26: Tier 2 | E26: 3 | F26: 7 | G26: 4 | H26: 443000 | I26: 26580 | J26: 6547.7445 | K26: 26580 | L26: 502707.74 | M26: 590.66667 | N26: 2658 | O26: 240 | P26: 200 | Q26: 3688.6667 | R26: 4430 | S26: 6032.4929 | T26: 13290 | U26: 15081.232 | V26: =L26-H26 -> 59707.745 | Z26: =Z25+1 -> 27 | AA26: =SUMIF(final_phase2_full_costs!F10:F405,Z26,final_phase2_full_costs!H10:H405) -> 14402000
A27: 39 | B27: Dallas | C27: 1 | D27: Tier 2 | E27: 3 | F27: 7 | G27: 4 | H27: 443000 | I27: 26580 | J27: 6547.7445 | K27: 26580 | L27: 502707.74 | M27: 590.66667 | N27: 2658 | O27: 240 | P27: 200 | Q27: 3688.6667 | R27: 4430 | S27: 6032.4929 | T27: 13290 | U27: 15081.232 | V27: =L27-H27 -> 59707.745 | Z27: =Z26+1 -> 28 | AA27: =SUMIF(final_phase2_full_costs!F11:F406,Z27,final_phase2_full_costs!H11:H406) -> 15059000
A28: 42 | B28: Dallas | C28: 1 | D28: Tier 2 | E28: 3 | F28: 7 | G28: 4 | H28: 443000 | I28: 26580 | J28: 6547.7445 | K28: 26580 | L28: 502707.74 | M28: 590.66667 | N28: 2658 | O28: 240 | P28: 200 | Q28: 3688.6667 | R28: 4430 | S28: 6032.4929 | T28: 13290 | U28: 15081.232 | V28: =L28-H28 -> 59707.745 | Z28: =Z27+1 -> 29 | AA28: =SUMIF(final_phase2_full_costs!F12:F407,Z28,final_phase2_full_costs!H12:H407) -> 8611000
A29: 47 | B29: Dallas | C29: 1 | D29: Tier 1 | E29: 4 | F29: 7 | G29: 3 | H29: 338000 | I29: 27040 | J29: 3330.4514 | K29: 27040 | L29: 395410.45 | M29: 338 | N29: 1521 | O29: 180 | P29: 150 | Q29: 2189 | R29: 3380 | S29: 4744.9254 | T29: 10140 | U29: 11862.314 | V29: =L29-H29 -> 57410.451 | Z29: =Z28+1 -> 30 | AA29: =SUMIF(final_phase2_full_costs!F13:F408,Z29,final_phase2_full_costs!H13:H408) -> 6830000
... A32: 53 | B32: Dallas | C32: 1 | D32: Tier 1 | E32: 4 | F32: 7 | G32: 3 | H32: 338000 | I32: 27040 | J32: 3330.4514 | K32: 27040 | L32: 395410.45 | M32: 338 | N32: 1521 | O32: 180 | P32: 150 | Q32: 2189 | R32: 3380 | S32: 4744.9254 | T32: 10140 | U32: 11862.314 | V32: =L32-H32 -> 57410.451 | Z32: =Z31+1 -> 33 | AA32: =SUMIF(final_phase2_full_costs!F16:F411,Z32,final_phase2_full_costs!H16:H411) -> 630000
V33: =SUM(V17:V32) -> 976509.66 | Z33: =Z32+1 -> 34 | AA33: =SUMIF(final_phase2_full_costs!F17:F412,Z33,final_phase2_full_costs!H17:H412) -> 0
A34: 17 | B34: Dallas | C34: 1 | D34: Tier 2 | E34: 2 | F34: 8 | G34: 6 | H34: 443000 | I34: 26580 | J34: 9857.8199 | K34: 26580 | L34: 506017.82 | M34: 886 | N34: 3987 | O34: 360 | P34: 300 | Q34: 5533 | R34: 4430 | S34: 6072.2138 | T34: 13290 | U34: 15180.535 | V34: =L34-H34 -> 63017.82 | Z34: =Z33+1 -> 35 | AA34: =SUMIF(final_phase2_full_costs!F18:F413,Z34,final_phase2_full_costs!H18:H413) -> 0
A35: 18 | B35: Dallas | C35: 1 | D35: Tier 2 | E35: 2 | F35: 8 | G35: 6 | H35: 443000 | I35: 26580 | J35: 9857.8199 | K35: 26580 | L35: 506017.82 | M35: 886 | N35: 3987 | O35: 360 | P35: 300 | Q35: 5533 | R35: 4430 | S35: 6072.2138 | T35: 13290 | U35: 15180.535 | V35: =L35-H35 -> 63017.82
A36: 19 | B36: Dallas | C36: 1 | D36: Tier 2 | E36: 2 | F36: 8 | G36: 6 | H36: 443000 | I36: 26580 | J36: 9857.8199 | K36: 26580 | L36: 506017.82 | M36: 886 | N36: 3987 | O36: 360 | P36: 300 | Q36: 5533 | R36: 4430 | S36: 6072.2138 | T36: 13290 | U36: 15180.535 | V36: =L36-H36 -> 63017.82
A37: 20 | B37: Dallas | C37: 1 | D37: Tier 2 | E37: 2 | F37: 8 | G37: 6 | H37: 443000 | I37: 26580 | J37: 9857.8199 | K37: 26580 | L37: 506017.82 | M37: 886 | N37: 3987 | O37: 360 | P37: 300 | Q37: 5533 | R37: 4430 | S37: 6072.2138 | T37: 13290 | U37: 15180.535 | V37: =L37-H37 -> 63017.82
A38: 22 | B38: Dallas | C38: 1 | D38: Tier 2 | E38: 2 | F38: 8 | G38: 6 | H38: 443000 | I38: 26580 | J38: 9857.8199 | K38: 26580 | L38: 506017.82 | M38: 886 | N38: 3987 | O38: 360 | P38: 300 | Q38: 5533 | R38: 4430 | S38: 6072.2138 | T38: 13290 | U38: 15180.535 | V38: =L38-H38 -> 63017.82
A39: 24 | B39: Dallas | C39: 1 | D39: Tier 3 | E39: 2 | F39: 8 | G39: 6 | H39: 676000 | I39: 33800 | J39: 16693.872 | K39: 33800 | L39: 760293.87 | M39: 1352 | N39: 6084 | O39: 360 | P39: 300 | Q39: 8096 | R39: 6760 | S39: 9123.5265 | T39: 20280 | U39: 22808.816 | V39: =L39-H39 -> 84293.872
A40: 25 | B40: Dallas | C40: 1 | D40: Tier 3 | E40: 2 | F40: 8 | G40: 6 | H40: 676000 | I40: 33800 | J40: 16693.872 | K40: 33800 | L40: 760293.87 | M40: 1352 | N40: 6084 | O40: 360 | P40: 300 | Q40: 8096 | R40: 6760 | S40: 9123.5265 | T40: 20280 | U40: 22808.816 | V40: =L40-H40 -> 84293.872
A41: 26 | B41: Dallas | C41: 1 | D41: Tier 1 | E41: 3 | F41: 8 | G41: 5 | H41: 338000 | I41: 27040 | J41: 5568.9637 | K41: 27040 | L41: 397648.96 | M41: 563.33333 | N41: 2535 | O41: 300 | P41: 250 | Q41: 3648.3333 | R41: 3380 | S41: 4771.7876 | T41: 10140 | U41: 11929.469 | V41: =L41-H41 -> 59648.964
A42: 27 | B42: Dallas | C42: 1 | D42: Tier 1 | E42: 3 | F42: 8 | G42: 5 | H42: 338000 | I42: 27040 | J42: 5568.9637 | K42: 27040 | L42: 397648.96 | M42: 563.33333 | N42: 2535 | O42: 300 | P42: 250 | Q42: 3648.3333 | R42: 3380 | S42: 4771.7876 | T42: 10140 | U42: 11929.469 | V42: =L42-H42 -> 59648.964
A43: 30 | B43: Dallas | C43: 1 | D43: Tier 1 | E43: 3 | F43: 8 | G43: 5 | H43: 338000 | I43: 27040 | J43: 5568.9637 | K43: 27040 | L43: 397648.96 | M43: 563.33333 | N43: 2535 | O43: 300 | P43: 250 | Q43: 3648.3333 | R43: 3380 | S43: 4771.7876 | T43: 10140 | U43: 11929.469 | V43: =L43-H43 -> 59648.964
A44: 33 | B44: Dallas | C44: 1 | D44: Tier 2 | E44: 3 | F44: 8 | G44: 5 | H44: 443000 | I44: 26580 | J44: 8199.7468 | K44: 26580 | L44: 504359.75 | M44: 738.33333 | N44: 3322.5 | O44: 300 | P44: 250 | Q44: 4610.8333 | R44: 4430 | S44: 6052.317 | T44: 13290 | U44: 15130.792 | V44: =L44-H44 -> 61359.747
A45: 40 | B45: Dallas | C45: 1 | D45: Tier 2 | E45: 3 | F45: 8 | G45: 5 | H45: 443000 | I45: 26580 | J45: 8199.7468 | K45: 26580 | L45: 504359.75 | M45: 738.33333 | N45: 3322.5 | O45: 300 | P45: 250 | Q45: 4610.8333 | R45: 4430 | S45: 6052.317 | T45: 13290 | U45: 15130.792 | V45: =L45-H45 -> 61359.747
A46: 43 | B46: Dallas | C46: 1 | D46: Tier 3 | E46: 3 | F46: 8 | G46: 5 | H46: 676000 | I46: 33800 | J46: 13883.202 | K46: 33800 | L46: 757483.2 | M46: 1126.6667 | N46: 5070 | O46: 300 | P46: 250 | Q46: 6746.6667 | R46: 6760 | S46: 9089.7984 | T46: 20280 | U46: 22724.496 | V46: =L46-H46 -> 81483.202
... A60: 82 | B60: Dallas | C60: 1 | D60: Tier 1 | E60: 5 | F60: 8 | G60: 3 | H60: 338000 | I60: 27040 | J60: 3330.4514 | K60: 27040 | L60: 395410.45 | M60: 338 | N60: 1521 | O60: 180 | P60: 150 | Q60: 2189 | R60: 3380 | S60: 4744.9254 | T60: 10140 | U60: 11862.314 | V60: =L60-H60 -> 57410.451
V61: =SUM(V34:V60) -> 1733494.6
A62: 34 | B62: Dallas | C62: 1 | D62: Tier 2 | E62: 3 | F62: 9 | G62: 6 | H62: 443000 | I62: 26580 | J62: 9857.8199 | K62: 26580 | L62: 506017.82 | M62: 886 | N62: 3987 | O62: 360 | P62: 300 | Q62: 5533 | R62: 4430 | S62: 6072.2138 | T62: 13290 | U62: 15180.535 | V62: =L62-H62 -> 63017.82
A63: 35 | B63: Dallas | C63: 1 | D63: Tier 2 | E63: 3 | F63: 9 | G63: 6 | H63: 443000 | I63: 26580 | J63: 9857.8199 | K63: 26580 | L63: 506017.82 | M63: 886 | N63: 3987 | O63: 360 | P63: 300 | Q63: 5533 | R63: 4430 | S63: 6072.2138 | T63: 13290 | U63: 15180.535 | V63: =L63-H63 -> 63017.82
A64: 37 | B64: Dallas | C64: 1 | D64: Tier 2 | E64: 3 | F64: 9 | G64: 6 | H64: 443000 | I64: 26580 | J64: 9857.8199 | K64: 26580 | L64: 506017.82 | M64: 886 | N64: 3987 | O64: 360 | P64: 300 | Q64: 5533 | R64: 4430 | S64: 6072.2138 | T64: 13290 | U64: 15180.535 | V64: =L64-H64 -> 63017.82
A65: 38 | B65: Dallas | C65: 1 | D65: Tier 2 | E65: 3 | F65: 9 | G65: 6 | H65: 443000 | I65: 26580 | J65: 9857.8199 | K65: 26580 | L65: 506017.82 | M65: 886 | N65: 3987 | O65: 360 | P65: 300 | Q65: 5533 | R65: 4430 | S65: 6072.2138 | T65: 13290 | U65: 15180.535 | V65: =L65-H65 -> 63017.82
A66: 41 | B66: Dallas | C66: 1 | D66: Tier 2 | E66: 3 | F66: 9 | G66: 6 | H66: 443000 | I66: 26580 | J66: 9857.8199 | K66: 26580 | L66: 506017.82 | M66: 886 | N66: 3987 | O66: 360 | P66: 300 | Q66: 5533 | R66: 4430 | S66: 6072.2138 | T66: 13290 | U66: 15180.535 | V66: =L66-H66 -> 63017.82
A67: 60 | B67: Dallas | C67: 1 | D67: Tier 2 | E67: 4 | F67: 9 | G67: 5 | H67: 443000 | I67: 26580 | J67: 8199.7468 | K67: 26580 | L67: 504359.75 | M67: 738.33333 | N67: 3322.5 | O67: 300 | P67: 250 | Q67: 4610.8333 | R67: 4430 | S67: 6052.317 | T67: 13290 | U67: 15130.792 | V67: =L67-H67 -> 61359.747
A68: 61 | B68: Dallas | C68: 1 | D68: Tier 2 | E68: 4 | F68: 9 | G68: 5 | H68: 443000 | I68: 26580 | J68: 8199.7468 | K68: 26580 | L68: 504359.75 | M68: 738.33333 | N68: 3322.5 | O68: 300 | P68: 250 | Q68: 4610.8333 | R68: 4430 | S68: 6052.317 | T68: 13290 | U68: 15130.792 | V68: =L68-H68 -> 61359.747
A69: 63 | B69: Dallas | C69: 1 | D69: Tier 2 | E69: 4 | F69: 9 | G69: 5 | H69: 443000 | I69: 26580 | J69: 8199.7468 | K69: 26580 | L69: 504359.75 | M69: 738.33333 | N69: 3322.5 | O69: 300 | P69: 250 | Q69: 4610.8333 | R69: 4430 | S69: 6052.317 | T69: 13290 | U69: 15130.792 | V69: =L69-H69 -> 61359.747
A70: 65 | B70: Dallas | C70: 1 | D70: Tier 2 | E70: 4 | F70: 9 | G70: 5 | H70: 443000 | I70: 26580 | J70: 8199.7468 | K70: 26580 | L70: 504359.75 | M70: 738.33333 | N70: 3322.5 | O70: 300 | P70: 250 | Q70: 4610.8333 | R70: 4430 | S70: 6052.317 | T70: 13290 | U70: 15130.792 | V70: =L70-H70 -> 61359.747
A71: 67 | B71: Dallas | C71: 1 | D71: Tier 3 | E71: 4 | F71: 9 | G71: 5 | H71: 676000 | I71: 33800 | J71: 13883.202 | K71: 33800 | L71: 757483.2 | M71: 1126.6667 | N71: 5070 | O71: 300 | P71: 250 | Q71: 6746.6667 | R71: 6760 | S71: 9089.7984 | T71: 20280 | U71: 22724.496 | V71: =L71-H71 -> 81483.202
A72: 69 | B72: Dallas | C72: 1 | D72: Tier 3 | E72: 4 | F72: 9 | G72: 5 | H72: 676000 | I72: 33800 | J72: 13883.202 | K72: 33800 | L72: 757483.2 | M72: 1126.6667 | N72: 5070 | O72: 300 | P72: 250 | Q72: 6746.6667 | R72: 6760 | S72: 9089.7984 | T72: 20280 | U72: 22724.496 | V72: =L72-H72 -> 81483.202
A73: 71 | B73: Dallas | C73: 1 | D73: Tier 1 | E73: 5 | F73: 9 | G73: 4 | H73: 338000 | I73: 27040 | J73: 4447.8785 | K73: 27040 | L73: 396527.88 | M73: 450.66667 | N73: 2028 | O73: 240 | P73: 200 | Q73: 2918.6667 | R73: 3380 | S73: 4758.3345 | T73: 10140 | U73: 11895.836 | V73: =L73-H73 -> 58527.878
... A88: 118 | B88: Dallas | C88: 1 | D88: Tier 1 | E88: 6 | F88: 9 | G88: 3 | H88: 338000 | I88: 27040 | J88: 3330.4514 | K88: 27040 | L88: 395410.45 | M88: 338 | N88: 1521 | O88: 180 | P88: 150 | Q88: 2189 | R88: 3380 | S88: 4744.9254 | T88: 10140 | U88: 11862.314 | V88: =L88-H88 -> 57410.451
V89: =SUM(V62:V88) -> 1660252.7
A90: 56 | B90: Dallas | C90: 1 | D90: Tier 2 | E90: 4 | F90: 10 | G90: 6 | H90: 443000 | I90: 26580 | J90: 9857.8199 | K90: 26580 | L90: 506017.82 | M90: 886 | N90: 3987 | O90: 360 | P90: 300 | Q90: 5533 | R90: 4430 | S90: 6072.2138 | T90: 13290 | U90: 15180.535 | V90: =L90-H90 -> 63017.82
A91: 58 | B91: Dallas | C91: 1 | D91: Tier 2 | E91: 4 | F91: 10 | G91: 6 | H91: 443000 | I91: 26580 | J91: 9857.8199 | K91: 26580 | L91: 506017.82 | M91: 886 | N91: 3987 | O91: 360 | P91: 300 | Q91: 5533 | R91: 4430 | S91: 6072.2138 | T91: 13290 | U91: 15180.535 | V91: =L91-H91 -> 63017.82
A92: 62 | B92: Dallas | C92: 1 | D92: Tier 2 | E92: 4 | F92: 10 | G92: 6 | H92: 443000 | I92: 26580 | J92: 9857.8199 | K92: 26580 | L92: 506017.82 | M92: 886 | N92: 3987 | O92: 360 | P92: 300 | Q92: 5533 | R92: 4430 | S92: 6072.2138 | T92: 13290 | U92: 15180.535 | V92: =L92-H92 -> 63017.82
A93: 64 | B93: Dallas | C93: 1 | D93: Tier 2 | E93: 4 | F93: 10 | G93: 6 | H93: 443000 | I93: 26580 | J93: 9857.8199 | K93: 26580 | L93: 506017.82 | M93: 886 | N93: 3987 | O93: 360 | P93: 300 | Q93: 5533 | R93: 4430 | S93: 6072.2138 | T93: 13290 | U93: 15180.535 | V93: =L93-H93 -> 63017.82
A94: 74 | B94: Dallas | C94: 1 | D94: Tier 1 | E94: 5 | F94: 10 | G94: 5 | H94: 338000 | I94: 27040 | J94: 5568.9637 | K94: 27040 | L94: 397648.96 | M94: 563.33333 | N94: 2535 | O94: 300 | P94: 250 | Q94: 3648.3333 | R94: 3380 | S94: 4771.7876 | T94: 10140 | U94: 11929.469 | V94: =L94-H94 -> 59648.964
A95: 76 | B95: Dallas | C95: 1 | D95: Tier 1 | E95: 5 | F95: 10 | G95: 5 | H95: 338000 | I95: 27040 | J95: 5568.9637 | K95: 27040 | L95: 397648.96 | M95: 563.33333 | N95: 2535 | O95: 300 | P95: 250 | Q95: 3648.3333 | R95: 3380 | S95: 4771.7876 | T95: 10140 | U95: 11929.469 | V95: =L95-H95 -> 59648.964
A96: 77 | B96: Dallas | C96: 1 | D96: Tier 1 | E96: 5 | F96: 10 | G96: 5 | H96: 338000 | I96: 27040 | J96: 5568.9637 | K96: 27040 | L96: 397648.96 | M96: 563.33333 | N96: 2535 | O96: 300 | P96: 250 | Q96: 3648.3333 | R96: 3380 | S96: 4771.7876 | T96: 10140 | U96: 11929.469 | V96: =L96-H96 -> 59648.964
A97: 83 | B97: Dallas | C97: 1 | D97: Tier 2 | E97: 5 | F97: 10 | G97: 5 | H97: 443000 | I97: 26580 | J97: 8199.7468 | K97: 26580 | L97: 504359.75 | M97: 738.33333 | N97: 3322.5 | O97: 300 | P97: 250 | Q97: 4610.8333 | R97: 4430 | S97: 6052.317 | T97: 13290 | U97: 15130.792 | V97: =L97-H97 -> 61359.747
A98: 84 | B98: Dallas | C98: 1 | D98: Tier 2 | E98: 5 | F98: 10 | G98: 5 | H98: 443000 | I98: 26580 | J98: 8199.7468 | K98: 26580 | L98: 504359.75 | M98: 738.33333 | N98: 3322.5 | O98: 300 | P98: 250 | Q98: 4610.8333 | R98: 4430 | S98: 6052.317 | T98: 13290 | U98: 15130.792 | V98: =L98-H98 -> 61359.747
A99: 87 | B99: Dallas | C99: 1 | D99: Tier 2 | E99: 5 | F99: 10 | G99: 5 | H99: 443000 | I99: 26580 | J99: 8199.7468 | K99: 26580 | L99: 504359.75 | M99: 738.33333 | N99: 3322.5 | O99: 300 | P99: 250 | Q99: 4610.8333 | R99: 4430 | S99: 6052.317 | T99: 13290 | U99: 15130.792 | V99: =L99-H99 -> 61359.747
A100: 93 | B100: Dallas | C100: 1 | D100: Tier 2 | E100: 5 | F100: 10 | G100: 5 | H100: 443000 | I100: 26580 | J100: 8199.7468 | K100: 26580 | L100: 504359.75 | M100: 738.33333 | N100: 3322.5 | O100: 300 | P100: 250 | Q100: 4610.8333 | R100: 4430 | S100: 6052.317 | T100: 13290 | U100: 15130.792 | V100: =L100-H100 -> 61359.747
A101: 97 | B101: Dallas | C101: 1 | D101: Tier 2 | E101: 5 | F101: 10 | G101: 5 | H101: 443000 | I101: 26580 | J101: 8199.7468 | K101: 26580 | L101: 504359.75 | M101: 738.33333 | N101: 3322.5 | O101: 300 | P101: 250 | Q101: 4610.8333 | R101: 4430 | S101: 6052.317 | T101: 13290 | U101: 15130.792 | V101: =L101-H101 -> 61359.747
... A119: 159 | B119: Dallas | C119: 1 | D119: Tier 1 | E119: 7 | F119: 10 | G119: 3 | H119: 338000 | I119: 27040 | J119: 3330.4514 | K119: 27040 | L119: 395410.45 | M119: 338 | N119: 1521 | O119: 180 | P119: 150 | Q119: 2189 | R119: 3380 | S119: 4744.9254 | T119: 10140 | U119: 11862.314 | V119: =L119-H119 -> 57410.451
V120: =SUM(V90:V119) -> 1862558.6
A121: 68 | B121: Dallas | C121: 1 | D121: Tier 3 | E121: 4 | F121: 11 | G121: 7 | H121: 676000 | I121: 33800 | J121: 19515.992 | K121: 33800 | L121: 763115.99 | M121: 1577.3333 | N121: 7098 | O121: 420 | P121: 350 | Q121: 9445.3333 | R121: 6760 | S121: 9157.3919 | T121: 20280 | U121: 22893.48 | V121: =L121-H121 -> 87115.992
A122: 70 | B122: Dallas | C122: 1 | D122: Tier 3 | E122: 4 | F122: 11 | G122: 7 | H122: 676000 | I122: 33800 | J122: 19515.992 | K122: 33800 | L122: 763115.99 | M122: 1577.3333 | N122: 7098 | O122: 420 | P122: 350 | Q122: 9445.3333 | R122: 6760 | S122: 9157.3919 | T122: 20280 | U122: 22893.48 | V122: =L122-H122 -> 87115.992
A123: 85 | B123: Dallas | C123: 1 | D123: Tier 2 | E123: 5 | F123: 11 | G123: 6 | H123: 443000 | I123: 26580 | J123: 9857.8199 | K123: 26580 | L123: 506017.82 | M123: 886 | N123: 3987 | O123: 360 | P123: 300 | Q123: 5533 | R123: 4430 | S123: 6072.2138 | T123: 13290 | U123: 15180.535 | V123: =L123-H123 -> 63017.82
A124: 88 | B124: Dallas | C124: 1 | D124: Tier 2 | E124: 5 | F124: 11 | G124: 6 | H124: 443000 | I124: 26580 | J124: 9857.8199 | K124: 26580 | L124: 506017.82 | M124: 886 | N124: 3987 | O124: 360 | P124: 300 | Q124: 5533 | R124: 4430 | S124: 6072.2138 | T124: 13290 | U124: 15180.535 | V124: =L124-H124 -> 63017.82
A125: 89 | B125: Dallas | C125: 1 | D125: Tier 2 | E125: 5 | F125: 11 | G125: 6 | H125: 443000 | I125: 26580 | J125: 9857.8199 | K125: 26580 | L125: 506017.82 | M125: 886 | N125: 3987 | O125: 360 | P125: 300 | Q125: 5533 | R125: 4430 | S125: 6072.2138 | T125: 13290 | U125: 15180.535 | V125: =L125-H125 -> 63017.82
A126: 91 | B126: Dallas | C126: 1 | D126: Tier 2 | E126: 5 | F126: 11 | G126: 6 | H126: 443000 | I126: 26580 | J126: 9857.8199 | K126: 26580 | L126: 506017.82 | M126: 886 | N126: 3987 | O126: 360 | P126: 300 | Q126: 5533 | R126: 4430 | S126: 6072.2138 | T126: 13290 | U126: 15180.535 | V126: =L126-H126 -> 63017.82
A127: 95 | B127: Dallas | C127: 1 | D127: Tier 2 | E127: 5 | F127: 11 | G127: 6 | H127: 443000 | I127: 26580 | J127: 9857.8199 | K127: 26580 | L127: 506017.82 | M127: 886 | N127: 3987 | O127: 360 | P127: 300 | Q127: 5533 | R127: 4430 | S127: 6072.2138 | T127: 13290 | U127: 15180.535 | V127: =L127-H127 -> 63017.82
A128: 99 | B128: Dallas | C128: 1 | D128: Tier 2 | E128: 5 | F128: 11 | G128: 6 | H128: 443000 | I128: 26580 | J128: 9857.8199 | K128: 26580 | L128: 506017.82 | M128: 886 | N128: 3987 | O128: 360 | P128: 300 | Q128: 5533 | R128: 4430 | S128: 6072.2138 | T128: 13290 | U128: 15180.535 | V128: =L128-H128 -> 63017.82
A129: 105 | B129: Dallas | C129: 1 | D129: Tier 3 | E129: 5 | F129: 11 | G129: 6 | H129: 676000 | I129: 33800 | J129: 16693.872 | K129: 33800 | L129: 760293.87 | M129: 1352 | N129: 6084 | O129: 360 | P129: 300 | Q129: 8096 | R129: 6760 | S129: 9123.5265 | T129: 20280 | U129: 22808.816 | V129: =L129-H129 -> 84293.872
A130: 114 | B130: Dallas | C130: 1 | D130: Tier 1 | E130: 6 | F130: 11 | G130: 5 | H130: 338000 | I130: 27040 | J130: 5568.9637 | K130: 27040 | L130: 397648.96 | M130: 563.33333 | N130: 2535 | O130: 300 | P130: 250 | Q130: 3648.3333 | R130: 3380 | S130: 4771.7876 | T130: 10140 | U130: 11929.469 | V130: =L130-H130 -> 59648.964
A131: 121 | B131: Dallas | C131: 1 | D131: Tier 2 | E131: 6 | F131: 11 | G131: 5 | H131: 443000 | I131: 26580 | J131: 8199.7468 | K131: 26580 | L131: 504359.75 | M131: 738.33333 | N131: 3322.5 | O131: 300 | P131: 250 | Q131: 4610.8333 | R131: 4430 | S131: 6052.317 | T131: 13290 | U131: 15130.792 | V131: =L131-H131 -> 61359.747
A132: 122 | B132: Dallas | C132: 1 | D132: Tier 2 | E132: 6 | F132: 11 | G132: 5 | H132: 443000 | I132: 26580 | J132: 8199.7468 | K132: 26580 | L132: 504359.75 | M132: 738.33333 | N132: 3322.5 | O132: 300 | P132: 250 | Q132: 4610.8333 | R132: 4430 | S132: 6052.317 | T132: 13290 | U132: 15130.792 | V132: =L132-H132 -> 61359.747
... A168: 197 | B168: Dallas | C168: 1 | D168: Tier 1 | E168: 8 | F168: 11 | G168: 3 | H168: 338000 | I168: 27040 | J168: 3330.4514 | K168: 27040 | L168: 395410.45 | M168: 338 | N168: 1521 | O168: 180 | P168: 150 | Q168: 2189 | R168: 3380 | S168: 4744.9254 | T168: 10140 | U168: 11862.314 | V168: =L168-H168 -> 57410.451
V169: =SUM(V121:V168) -> 2988036.7
A170: 101 | B170: Dallas | C170: 1 | D170: Tier 3 | E170: 5 | F170: 12 | G170: 7 | H170: 676000 | I170: 33800 | J170: 19515.992 | K170: 33800 | L170: 763115.99 | M170: 1577.3333 | N170: 7098 | O170: 420 | P170: 350 | Q170: 9445.3333 | R170: 6760 | S170: 9157.3919 | T170: 20280 | U170: 22893.48 | V170: =L170-H170 -> 87115.992
A171: 120 | B171: Dallas | C171: 1 | D171: Tier 2 | E171: 6 | F171: 12 | G171: 6 | H171: 443000 | I171: 26580 | J171: 9857.8199 | K171: 26580 | L171: 506017.82 | M171: 886 | N171: 3987 | O171: 360 | P171: 300 | Q171: 5533 | R171: 4430 | S171: 6072.2138 | T171: 13290 | U171: 15180.535 | V171: =L171-H171 -> 63017.82
A172: 124 | B172: Dallas | C172: 1 | D172: Tier 2 | E172: 6 | F172: 12 | G172: 6 | H172: 443000 | I172: 26580 | J172: 9857.8199 | K172: 26580 | L172: 506017.82 | M172: 886 | N172: 3987 | O172: 360 | P172: 300 | Q172: 5533 | R172: 4430 | S172: 6072.2138 | T172: 13290 | U172: 15180.535 | V172: =L172-H172 -> 63017.82
A173: 127 | B173: Dallas | C173: 1 | D173: Tier 2 | E173: 6 | F173: 12 | G173: 6 | H173: 443000 | I173: 26580 | J173: 9857.8199 | K173: 26580 | L173: 506017.82 | M173: 886 | N173: 3987 | O173: 360 | P173: 300 | Q173: 5533 | R173: 4430 | S173: 6072.2138 | T173: 13290 | U173: 15180.535 | V173: =L173-H173 -> 63017.82
A174: 129 | B174: Dallas | C174: 1 | D174: Tier 2 | E174: 6 | F174: 12 | G174: 6 | H174: 443000 | I174: 26580 | J174: 9857.8199 | K174: 26580 | L174: 506017.82 | M174: 886 | N174: 3987 | O174: 360 | P174: 300 | Q174: 5533 | R174: 4430 | S174: 6072.2138 | T174: 13290 | U174: 15180.535 | V174: =L174-H174 -> 63017.82
A175: 138 | B175: Dallas | C175: 1 | D175: Tier 2 | E175: 6 | F175: 12 | G175: 6 | H175: 443000 | I175: 26580 | J175: 9857.8199 | K175: 26580 | L175: 506017.82 | M175: 886 | N175: 3987 | O175: 360 | P175: 300 | Q175: 5533 | R175: 4430 | S175: 6072.2138 | T175: 13290 | U175: 15180.535 | V175: =L175-H175 -> 63017.82
A176: 140 | B176: Dallas | C176: 1 | D176: Tier 3 | E176: 6 | F176: 12 | G176: 6 | H176: 676000 | I176: 33800 | J176: 16693.872 | K176: 33800 | L176: 760293.87 | M176: 1352 | N176: 6084 | O176: 360 | P176: 300 | Q176: 8096 | R176: 6760 | S176: 9123.5265 | T176: 20280 | U176: 22808.816 | V176: =L176-H176 -> 84293.872
A177: 142 | B177: Dallas | C177: 1 | D177: Tier 3 | E177: 6 | F177: 12 | G177: 6 | H177: 676000 | I177: 33800 | J177: 16693.872 | K177: 33800 | L177: 760293.87 | M177: 1352 | N177: 6084 | O177: 360 | P177: 300 | Q177: 8096 | R177: 6760 | S177: 9123.5265 | T177: 20280 | U177: 22808.816 | V177: =L177-H177 -> 84293.872
A178: 144 | B178: Dallas | C178: 1 | D178: Tier 3 | E178: 6 | F178: 12 | G178: 6 | H178: 676000 | I178: 33800 | J178: 16693.872 | K178: 33800 | L178: 760293.87 | M178: 1352 | N178: 6084 | O178: 360 | P178: 300 | Q178: 8096 | R178: 6760 | S178: 9123.5265 | T178: 20280 | U178: 22808.816 | V178: =L178-H178 -> 84293.872
A179: 145 | B179: Dallas | C179: 1 | D179: Tier 3 | E179: 6 | F179: 12 | G179: 6 | H179: 676000 | I179: 33800 | J179: 16693.872 | K179: 33800 | L179: 760293.87 | M179: 1352 | N179: 6084 | O179: 360 | P179: 300 | Q179: 8096 | R179: 6760 | S179: 9123.5265 | T179: 20280 | U179: 22808.816 | V179: =L179-H179 -> 84293.872
A180: 149 | B180: Dallas | C180: 1 | D180: Tier 1 | E180: 7 | F180: 12 | G180: 5 | H180: 338000 | I180: 27040 | J180: 5568.9637 | K180: 27040 | L180: 397648.96 | M180: 563.33333 | N180: 2535 | O180: 300 | P180: 250 | Q180: 3648.3333 | R180: 3380 | S180: 4771.7876 | T180: 10140 | U180: 11929.469 | V180: =L180-H180 -> 59648.964
A181: 151 | B181: Dallas | C181: 1 | D181: Tier 1 | E181: 7 | F181: 12 | G181: 5 | H181: 338000 | I181: 27040 | J181: 5568.9637 | K181: 27040 | L181: 397648.96 | M181: 563.33333 | N181: 2535 | O181: 300 | P181: 250 | Q181: 3648.3333 | R181: 3380 | S181: 4771.7876 | T181: 10140 | U181: 11929.469 | V181: =L181-H181 -> 59648.964
...

Sheet Balance_Sheet
A1: Line Item | B1: Cash | C1: Inventory Value | D1: Total Assets | E1: Liabilities | F1: Equity
A2: Jan | B2: =Assumptions!B4+operation_exp!J2 -> 4.9541108e+08 | C2: =calculation_sheet!G2 -> 4243000 | D2: =B2+C2 -> 4.9965408e+08 | E2: =operation_exp!C2+operation_exp!A2+Assumptions!$C$17 -> 301997 | F2: =D2-E2 -> 4.9935208e+08
A3: Feb | B3: =Assumptions!$B$4+operation_exp!J3 -> 488243639 | C3: =C2+calculation_sheet!G3 -> 10829000 | D3: =B3+C3 -> 499072639 | E3: =operation_exp!C3+operation_exp!A3+Assumptions!$C$17 -> 301997 | F3: =D3-E3 -> 498770642
A4: Mar | B4: =Assumptions!$B$4+operation_exp!J4 -> 4.7874649e+08 | C4: =C3+calculation_sheet!G4 -> 19653000 | D4: =B4+C4 -> 4.9839949e+08 | E4: =operation_exp!C4+operation_exp!A4+Assumptions!$C$17 -> 301997 | F4: =D4-E4 -> 4.9809749e+08
A5: Apr | B5: =Assumptions!$B$4+operation_exp!J5 -> 4.6690016e+08 | C5: =C4+calculation_sheet!G5 -> 30715000 | D5: =B5+C5 -> 4.9761516e+08 | E5: =operation_exp!C5+operation_exp!A5+Assumptions!$C$17 -> 301997 | F5: =D5-E5 -> 4.9731316e+08
A6: May | B6: =Assumptions!$B$4+operation_exp!J6 -> 4.51349e+08 | C6: =C5+calculation_sheet!G6-final_phase1_full_costs!AA4 -> 45449000 | D6: =B6+C6 -> 4.96798e+08 | E6: =operation_exp!C6+operation_exp!A6+Assumptions!$C$17 -> 301997 | F6: =D6-E6 -> 4.9649601e+08
A7: Jun | B7: =Assumptions!$B$4+operation_exp!J7 -> 4.3757905e+08 | C7: =C6+calculation_sheet!G7-final_phase1_full_costs!AA5 -> 58959000 | D7: =B7+C7 -> 4.9653805e+08 | E7: =operation_exp!C7+operation_exp!A7+Assumptions!$C$17 -> 301997 | F7: =D7-E7 -> 4.9623606e+08
A8: Jul | B8: =Assumptions!$B$4+operation_exp!J8 -> 4.2653123e+08 | C8: =C7+calculation_sheet!G8-final_phase1_full_costs!AA6 -> 70126000 | D8: =B8+C8 -> 4.9665723e+08 | E8: =operation_exp!C8+operation_exp!A8+Assumptions!$C$17 -> 301997 | F8: =D8-E8 -> 4.9635523e+08
A9: Aug | B9: =Assumptions!$B$4+operation_exp!J9 -> 4.2420836e+08 | C9: =C8+calculation_sheet!G9-final_phase1_full_costs!AA7 -> 73565000 | D9: =B9+C9 -> 4.9777336e+08 | E9: =operation_exp!C9+operation_exp!A9+Assumptions!$C$17 -> 301997 | F9: =D9-E9 -> 4.9747136e+08
A10: Sep | B10: =Assumptions!$B$4+operation_exp!J10 -> 4.2350045e+08 | C10: =C9+calculation_sheet!G10-final_phase1_full_costs!AA8 -> 75360000 | D10: =B10+C10 -> 4.9886045e+08 | E10: =operation_exp!C10+operation_exp!A10+Assumptions!$C$17 -> 301997 | F10: =D10-E10 -> 4.9855845e+08
A11: Oct | B11: =Assumptions!$B$4+operation_exp!J11 -> 4.2625951e+08 | C11: =C10+calculation_sheet!G11-final_phase1_full_costs!AA9 -> 74008000 | D11: =B11+C11 -> 5.0026751e+08 | E11: =operation_exp!C11+operation_exp!A11+Assumptions!$C$17 -> 301997 | F11: =D11-E11 -> 4.9996551e+08
A12: Nov | B12: =Assumptions!$B$4+operation_exp!J12 -> 4.4339282e+08 | C12: =C11+calculation_sheet!G12-final_phase1_full_costs!AA10 -> 59868000 | D12: =B12+C12 -> 5.0326082e+08 | E12: =operation_exp!C12+operation_exp!A12+Assumptions!$C$17 -> 301997 | F12: =D12-E12 -> 5.0295883e+08
A13: Dec | B13: =Assumptions!$B$4+operation_exp!J13 -> 4.5227372e+08 | C13: =C12+calculation_sheet!G13-final_phase1_full_costs!AA11 -> 52373000 | D13: =B13+C13 -> 5.0464672e+08 | E13: =operation_exp!C13+operation_exp!A13+Assumptions!$C$17 -> 433997 | F13: =D13-E13 -> 5.0421272e+08
A14: Jan | B14: =Assumptions!$B$4+operation_exp!J14 -> 4.6479998e+08 | C14: =C13+calculation_sheet!G14-final_phase1_full_costs!AA12 -> 41649000 | D14: =B14+C14 -> 5.0644898e+08 | E14: =operation_exp!C14+operation_exp!A14+Assumptions!$C$17 -> 433997 | F14: =D14-E14 -> 5.0601498e+08
A15: Feb | B15: =Assumptions!$B$4+operation_exp!J15 -> 4.7203927e+08 | C15: =C14+calculation_sheet!G15-final_phase1_full_costs!AA13 -> 35611000 | D15: =B15+C15 -> 5.0765027e+08 | E15: =operation_exp!C15+operation_exp!A15+Assumptions!$C$17 -> 433997 | F15: =D15-E15 -> 5.0721627e+08
A16: Mar | B16: =Assumptions!$B$4+operation_exp!J16 -> 4.8166791e+08 | C16: =C15+calculation_sheet!G16-final_phase1_full_costs!AA14 -> 27696000 | D16: =B16+C16 -> 5.0936391e+08 | E16: =operation_exp!C16+operation_exp!A16+Assumptions!$C$17 -> 491995.8 | F16: =D16-E16 -> 5.0887191e+08
A17: Apr | B17: =Assumptions!$B$4+operation_exp!J17 -> 4.7658989e+08 | C17: =C16+calculation_sheet!G17-final_phase1_full_costs!AA15 -> 32857000 | D17: =B17+C17 -> 5.0944689e+08 | E17: =operation_exp!C17+operation_exp!A17+Assumptions!$C$17 -> 491995.8 | F17: =D17-E17 -> 5.0895489e+08
... A33: Aug | B33: =Assumptions!$B$4+operation_exp!J33 -> 5.2463438e+08 | C33: =C32+calculation_sheet!G33-final_phase1_full_costs!AA31 -> 630000 | D33: =B33+C33 -> 5.2526438e+08 | E33: =operation_exp!C33+operation_exp!A33+Assumptions!$C$17 -> 491995.8 | F33: =D33-E33 -> 5.2477238e+08
A34: Sep | B34: =Assumptions!$B$4+operation_exp!J34 -> 5.2477648e+08 | C34: =C33+calculation_sheet!G34-final_phase1_full_costs!AA32 -> 0 | D34: =B34+C34 -> 5.2477648e+08 | E34: 0 | F34: =D34-E34 -> 5.2477648e+08

Sheet Income_Statement
A1: Line Item | B1: Revenue | C1: Cost of Goods Sold (COGS) | D1: Gross Profit | E1: Total_Opex | F1: Net Income
A2: Jan | B2: =calculation_sheet!M2+operation_exp!E2+calculation_sheet!L2 -> 170120 | C2: =calculation_sheet!G2+calculation_sheet!H2+calculation_sheet!I2+calculation_sheet!J2 -> 4569168.8 | D2: =B2-C2 -> -4399048.8 | E2: =operation_exp!H2+operation_exp!E2+Assumptions!B110 -> 189876 | F2: =D2-E2 -> -4588924.8
A3: Feb | B3: =calculation_sheet!M3+operation_exp!E3+calculation_sheet!L3 -> 264340 | C3: =calculation_sheet!G3+calculation_sheet!H3+calculation_sheet!I3+calculation_sheet!J3+calculation_sheet!K3 -> 7089903.2 | D3: =B3-C3 -> -6825563.2 | E3: =operation_exp!H3+operation_exp!E3 -> 341873 | F3: =D3-E3 -> -7167436.2
A4: Mar | B4: =calculation_sheet!M4+operation_exp!E4+calculation_sheet!L4 -> 354420 | C4: =calculation_sheet!G4+calculation_sheet!H4+calculation_sheet!I4+calculation_sheet!J4+calculation_sheet!K4 -> 9509700.5 | D4: =B4-C4 -> -9155280.5 | E4: =operation_exp!H4+operation_exp!E4 -> 341873 | F4: =D4-E4 -> -9497153.5
A5: Apr | B5: =calculation_sheet!M5+operation_exp!E5+calculation_sheet!L5 -> 444700 | C5: =calculation_sheet!G5+calculation_sheet!H5+calculation_sheet!I5+calculation_sheet!J5+calculation_sheet!K5 -> 11934151 | D5: =B5-C5 -> -11489451 | E5: =operation_exp!H5+operation_exp!E5 -> 356873 | F5: =D5-E5 -> -11846324
A6: May | B6: =calculation_sheet!M6+operation_exp!E6+calculation_sheet!L6 -> 1444318 | C6: =calculation_sheet!G6+calculation_sheet!H6+calculation_sheet!I6+calculation_sheet!J6+calculation_sheet!K6 -> 16638604 | D6: =B6-C6 -> -15194286 | E6: =operation_exp!H6+operation_exp!E6 -> 356873 | F6: =D6-E6 -> -15551159
A7: Jun | B7: =calculation_sheet!M7+operation_exp!E7+calculation_sheet!L7 -> 5694907.1 | C7: =calculation_sheet!G7+calculation_sheet!H7+calculation_sheet!I7+calculation_sheet!J7+calculation_sheet!K7 -> 19107983 | D7: =B7-C7 -> -13413076 | E7: =operation_exp!H7+operation_exp!E7 -> 356873 | F7: =D7-E7 -> -13769949
A8: Jul | B8: =calculation_sheet!M8+operation_exp!E8+calculation_sheet!L8 -> 8466790 | C8: =calculation_sheet!G8+calculation_sheet!H8+calculation_sheet!I8+calculation_sheet!J8+calculation_sheet!K8 -> 19157739 | D8: =B8-C8 -> -10690949 | E8: =operation_exp!H8+operation_exp!E8 -> 356873 | F8: =D8-E8 -> -11047822
A9: Aug | B9: =calculation_sheet!M9+operation_exp!E9+calculation_sheet!L9 -> 14874974 | C9: =calculation_sheet!G9+calculation_sheet!H9+calculation_sheet!I9+calculation_sheet!J9+calculation_sheet!K9 -> 16825974 | D9: =B9-C9 -> -1950999.8 | E9: =operation_exp!H9+operation_exp!E9 -> 371873 | F9: =D9-E9 -> -2322872.8
A10: Sep | B10: =calculation_sheet!M10+operation_exp!E10+calculation_sheet!L10 -> 13978823 | C10: =calculation_sheet!G10+calculation_sheet!H10+calculation_sheet!I10+calculation_sheet!J10+calculation_sheet!K10 -> 14314863 | D10: =B10-C10 -> -336039.68 | E10: =operation_exp!H10+operation_exp!E10 -> 371873 | F10: =D10-E10 -> -707912.68
A11: Oct | B11: =calculation_sheet!M11+operation_exp!E11+calculation_sheet!L11 -> 15297341 | C11: =calculation_sheet!G11+calculation_sheet!H11+calculation_sheet!I11+calculation_sheet!J11+calculation_sheet!K11 -> 12166407 | D11: =B11-C11 -> 3130934 | E11: =operation_exp!H11+operation_exp!E11 -> 371873 | F11: =D11-E11 -> 2759061
A12: Nov | B12: =calculation_sheet!M12+operation_exp!E12+calculation_sheet!L12 -> 24933578 | C12: =calculation_sheet!G12+calculation_sheet!H12+calculation_sheet!I12+calculation_sheet!J12+calculation_sheet!K12 -> 7428388.4 | D12: =B12-C12 -> 17505190 | E12: =operation_exp!H12+operation_exp!E12 -> 371873 | F12: =D12-E12 -> 17133317
A13: Dec | B13: =calculation_sheet!M13+operation_exp!E13+calculation_sheet!L13 -> 14106548 | C13: =calculation_sheet!G13+calculation_sheet!H13+calculation_sheet!I13+calculation_sheet!J13+calculation_sheet!K13 -> 4802779 | D13: =B13-C13 -> 9303768.6 | E13: =operation_exp!H13+operation_exp!E13 -> 382873 | F13: =D13-E13 -> 8920895.6
A14: Jan | B14: =calculation_sheet!M14+operation_exp!E14+calculation_sheet!L14 -> 16639409 | C14: =calculation_sheet!G14+calculation_sheet!H14+calculation_sheet!I14+calculation_sheet!J14+calculation_sheet!K14 -> 3598273.6 | D14: =B14-C14 -> 13041135 | E14: =operation_exp!H14+operation_exp!E14 -> 514873 | F14: =D14-E14 -> 12526262
A15: Feb | B15: =calculation_sheet!M15+operation_exp!E15+calculation_sheet!L15 -> 12519928 | C15: =calculation_sheet!G15+calculation_sheet!H15+calculation_sheet!I15+calculation_sheet!J15+calculation_sheet!K15 -> 4758341 | D15: =B15-C15 -> 7761586.6 | E15: =operation_exp!H15+operation_exp!E15 -> 522298 | F15: =D15-E15 -> 7239288.6
A16: Mar | B16: =calculation_sheet!M16+operation_exp!E16+calculation_sheet!L16 -> 16497876 | C16: =calculation_sheet!G16+calculation_sheet!H16+calculation_sheet!I16+calculation_sheet!J16+calculation_sheet!K16 -> 6340463.4 | D16: =B16-C16 -> 10157412 | E16: =operation_exp!H16+operation_exp!E16+Assumptions!B121 -> 568774 | F16: =D16-E16 -> 9588638.4
A17: Apr | B17: =calculation_sheet!M17+operation_exp!E17+calculation_sheet!L17 -> 8749103.8 | C17: =calculation_sheet!G17+calculation_sheet!H17+calculation_sheet!I17+calculation_sheet!J17+calculation_sheet!K17 -> 13220353 | D17: =B17-C17 -> -4471249.4 | E17: =operation_exp!H17+operation_exp!E17 -> 606772.8 | F17: =D17-E17 -> -5078022.2
A18: May | B18: =calculation_sheet!M18+operation_exp!E18+calculation_sheet!L18 -> 7987128.9 | C18: =calculation_sheet!G18+calculation_sheet!H18+calculation_sheet!I18+calculation_sheet!J18+calculation_sheet!K18 -> 15863712 | D18: =B18-C18 -> -7876583.3 | E18: =operation_exp!H18+operation_exp!E18 -> 606772.8 | F18: =D18-E18 -> -8483356.1
A19: Jun | B19: =calculation_sheet!M19+operation_exp!E19+calculation_sheet!L19 -> 6795864.9 | C19: =calculation_sheet!G19+calculation_sheet!H19+calculation_sheet!I19+calculation_sheet!J19+calculation_sheet!K19 -> 22929633 | D19: =B19-C19 -> -16133769 | E19: =operation_exp!H19+operation_exp!E19 -> 606772.8 | F19: =D19-E19 -> -16740541
A20: Jul | B20: =calculation_sheet!M20+operation_exp!E20+calculation_sheet!L20 -> 6994921.9 | C20: =calculation_sheet!G20+calculation_sheet!H20+calculation_sheet!I20+calculation_sheet!J20+calculation_sheet!K20 -> 24415751 | D20: =B20-C20 -> -17420829 | E20: =operation_exp!H20+operation_exp!E20 -> 606772.8 | F20: =D20-E20 -> -18027602
A21: Aug | B21: =calculation_sheet!M21+operation_exp!E21+calculation_sheet!L21 -> 6403262.7 | C21: =calculation_sheet!G21+calculation_sheet!H21+calculation_sheet!I21+calculation_sheet!J21+calculation_sheet!K21 -> 23522830 | D21: =B21-C21 -> -17119567 | E21: =operation_exp!H21+operation_exp!E21 -> 606772.8 | F21: =D21-E21 -> -17726340
A22: Sep | B22: =calculation_sheet!M22+operation_exp!E22+calculation_sheet!L22 -> 12405881 | C22: =calculation_sheet!G22+calculation_sheet!H22+calculation_sheet!I22+calculation_sheet!J22+calculation_sheet!K22 -> 22280087 | D22: =B22-C22 -> -9874205.9 | E22: =operation_exp!H22+operation_exp!E22 -> 606772.8 | F22: =D22-E22 -> -10480979
A23: Oct | B23: =calculation_sheet!M23+operation_exp!E23+calculation_sheet!L23 -> 17317271 | C23: =calculation_sheet!G23+calculation_sheet!H23+calculation_sheet!I23+calculation_sheet!J23+calculation_sheet!K23 -> 15379764 | D23: =B23-C23 -> 1937506.5 | E23: =operation_exp!H23+operation_exp!E23 -> 606772.8 | F23: =D23-E23 -> 1330733.7
A24: Nov | B24: =calculation_sheet!M24+operation_exp!E24+calculation_sheet!L24 -> 28073284 | C24: =calculation_sheet!G24+calculation_sheet!H24+calculation_sheet!I24+calculation_sheet!J24+calculation_sheet!K24 -> 11125750 | D24: =B24-C24 -> 16947534 | E24: =operation_exp!H24+operation_exp!E24 -> 606772.8 | F24: =D24-E24 -> 16340762
A25: Dec | B25: =calculation_sheet!M25+operation_exp!E25+calculation_sheet!L25 -> 17136456 | C25: =calculation_sheet!G25+calculation_sheet!H25+calculation_sheet!I25+calculation_sheet!J25+calculation_sheet!K25 -> 8575187 | D25: =B25-C25 -> 8561268.6 | E25: =operation_exp!H25+operation_exp!E25 -> 606772.8 | F25: =D25-E25 -> 7954495.8
A26: Jan | B26: =calculation_sheet!M26+operation_exp!E26+calculation_sheet!L26 -> 22594460 | C26: =calculation_sheet!G26+calculation_sheet!H26+calculation_sheet!I26+calculation_sheet!J26+calculation_sheet!K26 -> 330461.26 | D26: =B26-C26 -> 22263999 | E26: =operation_exp!H26+operation_exp!E26 -> 626772.8 | F26: =D26-E26 -> 21637226
A27: Feb | B27: =calculation_sheet!M27+operation_exp!E27+calculation_sheet!L27 -> 19550570 | C27: =calculation_sheet!G27+calculation_sheet!H27+calculation_sheet!I27+calculation_sheet!J27+calculation_sheet!K27 -> 272290.1 | D27: =B27-C27 -> 19278280 | E27: =operation_exp!H27+operation_exp!E27 -> 626772.8 | F27: =D27-E27 -> 18651507
A28: Mar | B28: =calculation_sheet!M28+operation_exp!E28+calculation_sheet!L28 -> 17445394 | C28: =calculation_sheet!G28+calculation_sheet!H28+calculation_sheet!I28+calculation_sheet!J28+calculation_sheet!K28 -> 225882.9 | D28: =B28-C28 -> 17219511 | E28: =operation_exp!H28+operation_exp!E28 -> 626772.8 | F28: =D28-E28 -> 16592738
... A34: Sep | B34: =calculation_sheet!M34+operation_exp!E34+calculation_sheet!L34 -> 776114.34 | C34: =calculation_sheet!G34+calculation_sheet!H34+calculation_sheet!I34+calculation_sheet!J34+calculation_sheet!K34 -> 7244.0704 | D34: =B34-C34 -> 768870.27 | E34: =operation_exp!H34+operation_exp!E34 -> 626772.8 | F34: =D34-E34 -> 142097.47
F36: =SUM(F2:F34) -> 24776476

Sheet cash flow
A1: Line Item | B1: Cash Flow from Operating Activities (CFO) | C1: Cash Flow from Investing Activities (CFI) | D1: Net Change in Cash | E1: Beginning Cash | F1: ending cash
A2: Jan | B2: =operation_exp!I2 -> -4438924.8 | C2: -150000 | D2: =B2+C2 -> -4588924.8 | E2: 500000000 | F2: =E2+D2 -> 4.9541108e+08
A3: Feb | B3: =operation_exp!I3 -> -7167436.2 | D3: =B3+C3 -> -7167436.2 | E3: =F2 -> 4.9541108e+08 | F3: =E3+D3 -> 488243639
A4: Mar | B4: =operation_exp!I4 -> -9497153.5 | D4: =B4+C4 -> -9497153.5 | E4: =F3 -> 488243639 | F4: =E4+D4 -> 4.7874649e+08
A5: Apr | B5: =operation_exp!I5 -> -11846324 | D5: =B5+C5 -> -11846324 | E5: =F4 -> 4.7874649e+08 | F5: =E5+D5 -> 4.6690016e+08
A6: May | B6: =operation_exp!I6 -> -15551159 | D6: =B6+C6 -> -15551159 | E6: =F5 -> 4.6690016e+08 | F6: =E6+D6 -> 4.51349e+08
A7: Jun | B7: =operation_exp!I7 -> -13769949 | D7: =B7+C7 -> -13769949 | E7: =F6 -> 4.51349e+08 | F7: =E7+D7 -> 4.3757905e+08
A8: Jul | B8: =operation_exp!I8 -> -11047822 | D8: =B8+C8 -> -11047822 | E8: =F7 -> 4.3757905e+08 | F8: =E8+D8 -> 4.2653123e+08
A9: Aug | B9: =operation_exp!I9 -> -2322872.8 | D9: =B9+C9 -> -2322872.8 | E9: =F8 -> 4.2653123e+08 | F9: =E9+D9 -> 4.2420836e+08
A10: Sep | B10: =operation_exp!I10 -> -707912.68 | D10: =B10+C10 -> -707912.68 | E10: =F9 -> 4.2420836e+08 | F10: =E10+D10 -> 4.2350045e+08
A11: Oct | B11: =operation_exp!I11 -> 2759061 | D11: =B11+C11 -> 2759061 | E11: =F10 -> 4.2350045e+08 | F11: =E11+D11 -> 4.2625951e+08
A12: Nov | B12: =operation_exp!I12 -> 17133317 | D12: =B12+C12 -> 17133317 | E12: =F11 -> 4.2625951e+08 | F12: =E12+D12 -> 4.4339282e+08
A13: Dec | B13: =operation_exp!I13 -> 8920895.6 | D13: =B13+C13 -> 8920895.6 | E13: =F12 -> 4.4339282e+08 | F13: =E13+D13 -> 4.5231372e+08
A14: Jan | B14: =operation_exp!I14 -> 12526262 | C14: -40000 | D14: =B14+C14 -> 12486262 | E14: =F13 -> 4.5231372e+08 | F14: =E14+D14 -> 4.6479998e+08
A15: Feb | B15: =operation_exp!I15 -> 7239288.6 | D15: =B15+C15 -> 7239288.6 | E15: =F14 -> 4.6479998e+08 | F15: =E15+D15 -> 4.7203927e+08
A16: Mar | B16: =operation_exp!I16 -> 9628638.4 | D16: =B16+C16 -> 9628638.4 | E16: =F15 -> 4.7203927e+08 | F16: =E16+D16 -> 4.8166791e+08
A17: Apr | B17: =operation_exp!I17 -> -5078022.2 | D17: =B17+C17 -> -5078022.2 | E17: =F16 -> 4.8166791e+08 | F17: =E17+D17 -> 4.7658989e+08
A18: May | B18: =operation_exp!I18 -> -8483356.1 | D18: =B18+C18 -> -8483356.1 | E18: =F17 -> 4.7658989e+08 | F18: =E18+D18 -> 4.6810653e+08
A19: Jun | B19: =operation_exp!I19 -> -16740541 | D19: =B19+C19 -> -16740541 | E19: =F18 -> 4.6810653e+08 | F19: =E19+D19 -> 4.5136599e+08
A20: Jul | B20: =operation_exp!I20 -> -18027602 | D20: =B20+C20 -> -18027602 | E20: =F19 -> 4.5136599e+08 | F20: =E20+D20 -> 4.3333839e+08
A21: Aug | B21: =operation_exp!I21 -> -17726340 | D21: =B21+C21 -> -17726340 | E21: =F20 -> 4.3333839e+08 | F21: =E21+D21 -> 4.1561205e+08
A22: Sep | B22: =operation_exp!I22 -> -10480979 | D22: =B22+C22 -> -10480979 | E22: =F21 -> 4.1561205e+08 | F22: =E22+D22 -> 4.0513107e+08
A23: Oct | B23: =operation_exp!I23 -> 1330733.7 | D23: =B23+C23 -> 1330733.7 | E23: =F22 -> 4.0513107e+08 | F23: =E23+D23 -> 4.064618e+08
A24: Nov | B24: =operation_exp!I24 -> 16340762 | D24: =B24+C24 -> 16340762 | E24: =F23 -> 4.064618e+08 | F24: =E24+D24 -> 4.2280256e+08
A25: Dec | B25: =operation_exp!I25 -> 7954495.8 | D25: =B25+C25 -> 7954495.8 | E25: =F24 -> 4.2280256e+08 | F25: =E25+D25 -> 4.3075706e+08
A26: Jan | B26: =operation_exp!I26 -> 21637226 | D26: =B26+C26 -> 21637226 | E26: =F25 -> 4.3075706e+08 | F26: =E26+D26 -> 4.5239429e+08
... A34: Sep | B34: =operation_exp!I34 -> 142097.47 | D34: =B34+C34 -> 142097.47 | E34: =F33 -> 5.2463438e+08 | F34: =E34+D34 -> 5.2477648e+08
